{
  "nameEnUS": "New Super Mario Bros. ",
  "id": "cb7c3bca-4a8b-4273-855a-bb6e47dfc5e3",
  "hardware": "Nintendo DS",
  "timestamp": 1761613200,
  "name": {
    "en-US": "New Super Mario Bros. ",
    "ja-JP": "New スーパーマリオブラザーズ",
    "en-GB": "New Super Mario Bros. ",
    "fr-FR": "New Super Mario Bros. ",
    "fr-CA": "New Super Mario Bros. ",
    "de-DE": "New Super Mario Bros. ",
    "nl-NL": "New Super Mario Bros. ",
    "it-IT": "New Super Mario Bros. ",
    "pt-PT": "New Super Mario Bros. ",
    "pt-BR": "New Super Mario Bros. ",
    "es-ES": "New Super Mario Bros. ",
    "es-MX": "New Super Mario Bros. ",
    "ru-RU": "New Super Mario Bros. ",
    "ko-KR": "뉴 슈퍼 마리오브라더스",
    "zh-CN": "New Super Mario Bros.",
    "zh-TW": "New Super Mario Bros."
  },
  "allTracksPlaylistId": "b9f123be-f1e3-4509-8f85-03f8113fb035",
  "tracks": [
    {
      "id": "fea0ef23-d4ac-4f41-bf08-daddd6363f03",
      "name": {
        "en-US": "Title Screen",
        "ja-JP": "タイトル",
        "en-GB": "Title Screen",
        "fr-FR": "Title Screen",
        "fr-CA": "Title Screen",
        "de-DE": "Title Screen",
        "nl-NL": "Title Screen",
        "it-IT": "Title Screen",
        "pt-PT": "Title Screen",
        "pt-BR": "Title Screen",
        "es-ES": "Title Screen",
        "es-MX": "Title Screen",
        "ru-RU": "Title Screen",
        "ko-KR": "Title Screen",
        "zh-CN": "Title Screen",
        "zh-TW": "Title Screen"
      }
    },
    {
      "id": "85b5fec0-315e-4630-a016-fbf88dbcc938",
      "name": {
        "en-US": "Prologue: Out for a Walk",
        "ja-JP": "プロローグ：ピクニック",
        "en-GB": "Prologue: Out for a Walk",
        "fr-FR": "Prologue: Out for a Walk",
        "fr-CA": "Prologue: Out for a Walk",
        "de-DE": "Prologue: Out for a Walk",
        "nl-NL": "Prologue: Out for a Walk",
        "it-IT": "Prologue: Out for a Walk",
        "pt-PT": "Prologue: Out for a Walk",
        "pt-BR": "Prologue: Out for a Walk",
        "es-ES": "Prologue: Out for a Walk",
        "es-MX": "Prologue: Out for a Walk",
        "ru-RU": "Prologue: Out for a Walk",
        "ko-KR": "Prologue: Out for a Walk",
        "zh-CN": "Prologue: Out for a Walk",
        "zh-TW": "Prologue: Out for a Walk"
      }
    },
    {
      "id": "ed3ab2f4-a041-4c57-b474-290024f7f68c",
      "name": {
        "en-US": "Prologue: Princess Peach Kidnapped",
        "ja-JP": "プロローグ：さらわれたピーチ姫",
        "en-GB": "Prologue: Princess Peach Kidnapped",
        "fr-FR": "Prologue: Princess Peach Kidnapped",
        "fr-CA": "Prologue: Princess Peach Kidnapped",
        "de-DE": "Prologue: Princess Peach Kidnapped",
        "nl-NL": "Prologue: Princess Peach Kidnapped",
        "it-IT": "Prologue: Princess Peach Kidnapped",
        "pt-PT": "Prologue: Princess Peach Kidnapped",
        "pt-BR": "Prologue: Princess Peach Kidnapped",
        "es-ES": "Prologue: Princess Peach Kidnapped",
        "es-MX": "Prologue: Princess Peach Kidnapped",
        "ru-RU": "Prologue: Princess Peach Kidnapped",
        "ko-KR": "Prologue: Princess Peach Kidnapped",
        "zh-CN": "Prologue: Princess Peach Kidnapped",
        "zh-TW": "Prologue: Princess Peach Kidnapped"
      }
    },
    {
      "id": "bdfe2705-c782-45c9-a302-2172cd4b0d71",
      "name": {
        "en-US": "World 1",
        "ja-JP": "WORLD 1 ",
        "en-GB": "World 1",
        "fr-FR": "World 1",
        "fr-CA": "World 1",
        "de-DE": "World 1",
        "nl-NL": "World 1",
        "it-IT": "World 1",
        "pt-PT": "World 1",
        "pt-BR": "World 1",
        "es-ES": "World 1",
        "es-MX": "World 1",
        "ru-RU": "World 1",
        "ko-KR": "World 1",
        "zh-CN": "World 1",
        "zh-TW": "World 1"
      }
    },
    {
      "id": "2ba9c7be-b7e3-4372-a597-86952959c42a",
      "name": {
        "en-US": "Ground Theme",
        "ja-JP": "地上のテーマ",
        "en-GB": "Ground Theme",
        "fr-FR": "Ground Theme",
        "fr-CA": "Ground Theme",
        "de-DE": "Ground Theme",
        "nl-NL": "Ground Theme",
        "it-IT": "Ground Theme",
        "pt-PT": "Ground Theme",
        "pt-BR": "Ground Theme",
        "es-ES": "Ground Theme",
        "es-MX": "Ground Theme",
        "ru-RU": "Ground Theme",
        "ko-KR": "Ground Theme",
        "zh-CN": "Ground Theme",
        "zh-TW": "Ground Theme"
      }
    },
    {
      "id": "4c4246c5-c44d-4d9c-b602-9d3366b277e3",
      "name": {
        "en-US": "Mega Mario",
        "ja-JP": "巨大マリオ",
        "en-GB": "Mega Mario",
        "fr-FR": "Mega Mario",
        "fr-CA": "Mega Mario",
        "de-DE": "Mega Mario",
        "nl-NL": "Mega Mario",
        "it-IT": "Mega Mario",
        "pt-PT": "Mega Mario",
        "pt-BR": "Mega Mario",
        "es-ES": "Mega Mario",
        "es-MX": "Mega Mario",
        "ru-RU": "Mega Mario",
        "ko-KR": "Mega Mario",
        "zh-CN": "Mega Mario",
        "zh-TW": "Mega Mario"
      }
    },
    {
      "id": "7fbec461-6c15-495d-bde1-6528551b59f4",
      "name": {
        "en-US": "Course Clear",
        "ja-JP": "コースクリア",
        "en-GB": "Course Clear",
        "fr-FR": "Course Clear",
        "fr-CA": "Course Clear",
        "de-DE": "Course Clear",
        "nl-NL": "Course Clear",
        "it-IT": "Course Clear",
        "pt-PT": "Course Clear",
        "pt-BR": "Course Clear",
        "es-ES": "Course Clear",
        "es-MX": "Course Clear",
        "ru-RU": "Course Clear",
        "ko-KR": "Course Clear",
        "zh-CN": "Course Clear",
        "zh-TW": "Course Clear"
      }
    },
    {
      "id": "91e63920-7284-449a-97a2-8813b383d3d7",
      "name": {
        "en-US": "World 2",
        "ja-JP": "WORLD 2 ",
        "en-GB": "World 2",
        "fr-FR": "World 2",
        "fr-CA": "World 2",
        "de-DE": "World 2",
        "nl-NL": "World 2",
        "it-IT": "World 2",
        "pt-PT": "World 2",
        "pt-BR": "World 2",
        "es-ES": "World 2",
        "es-MX": "World 2",
        "ru-RU": "World 2",
        "ko-KR": "World 2",
        "zh-CN": "World 2",
        "zh-TW": "World 2"
      }
    },
    {
      "id": "395de535-7901-46d6-8fd5-786211bb90ac",
      "name": {
        "en-US": "Desert Theme",
        "ja-JP": "砂漠のテーマ",
        "en-GB": "Desert Theme",
        "fr-FR": "Desert Theme",
        "fr-CA": "Desert Theme",
        "de-DE": "Desert Theme",
        "nl-NL": "Desert Theme",
        "it-IT": "Desert Theme",
        "pt-PT": "Desert Theme",
        "pt-BR": "Desert Theme",
        "es-ES": "Desert Theme",
        "es-MX": "Desert Theme",
        "ru-RU": "Desert Theme",
        "ko-KR": "Desert Theme",
        "zh-CN": "Desert Theme",
        "zh-TW": "Desert Theme"
      }
    },
    {
      "id": "dd3adffa-713a-4bf3-b516-e728c4e76830",
      "name": {
        "en-US": "Switch On!",
        "ja-JP": "スイッチ",
        "en-GB": "Switch On!",
        "fr-FR": "Switch On!",
        "fr-CA": "Switch On!",
        "de-DE": "Switch On!",
        "nl-NL": "Switch On!",
        "it-IT": "Switch On!",
        "pt-PT": "Switch On!",
        "pt-BR": "Switch On!",
        "es-ES": "Switch On!",
        "es-MX": "Switch On!",
        "ru-RU": "Switch On!",
        "ko-KR": "Switch On!",
        "zh-CN": "Switch On!",
        "zh-TW": "Switch On!"
      }
    },
    {
      "id": "aacdced4-5c1e-460f-8bed-6ac620407360",
      "name": {
        "en-US": "Underground Theme",
        "ja-JP": "地下のテーマ",
        "en-GB": "Underground Theme",
        "fr-FR": "Underground Theme",
        "fr-CA": "Underground Theme",
        "de-DE": "Underground Theme",
        "nl-NL": "Underground Theme",
        "it-IT": "Underground Theme",
        "pt-PT": "Underground Theme",
        "pt-BR": "Underground Theme",
        "es-ES": "Underground Theme",
        "es-MX": "Underground Theme",
        "ru-RU": "Underground Theme",
        "ko-KR": "Underground Theme",
        "zh-CN": "Underground Theme",
        "zh-TW": "Underground Theme"
      }
    },
    {
      "id": "3f014b9f-9a52-4673-9ebb-ab7fa4409ba5",
      "name": {
        "en-US": "Course Clear (Special)",
        "ja-JP": "コースクリア（特殊）\n",
        "en-GB": "Course Clear (Special)",
        "fr-FR": "Course Clear (Special)",
        "fr-CA": "Course Clear (Special)",
        "de-DE": "Course Clear (Special)",
        "nl-NL": "Course Clear (Special)",
        "it-IT": "Course Clear (Special)",
        "pt-PT": "Course Clear (Special)",
        "pt-BR": "Course Clear (Special)",
        "es-ES": "Course Clear (Special)",
        "es-MX": "Course Clear (Special)",
        "ru-RU": "Course Clear (Special)",
        "ko-KR": "Course Clear (Special)",
        "zh-CN": "Course Clear (Special)",
        "zh-TW": "Course Clear (Special)"
      }
    },
    {
      "id": "7963261c-5ade-4d0e-b3b4-2b288b038e49",
      "name": {
        "en-US": "World 3",
        "ja-JP": "WORLD 3 ",
        "en-GB": "World 3",
        "fr-FR": "World 3",
        "fr-CA": "World 3",
        "de-DE": "World 3",
        "nl-NL": "World 3",
        "it-IT": "World 3",
        "pt-PT": "World 3",
        "pt-BR": "World 3",
        "es-ES": "World 3",
        "es-MX": "World 3",
        "ru-RU": "World 3",
        "ko-KR": "World 3",
        "zh-CN": "World 3",
        "zh-TW": "World 3"
      }
    },
    {
      "id": "94173506-5d26-418e-99fa-ee224d18cc97",
      "name": {
        "en-US": "Beach Theme",
        "ja-JP": "水辺のテーマ",
        "en-GB": "Beach Theme",
        "fr-FR": "Beach Theme",
        "fr-CA": "Beach Theme",
        "de-DE": "Beach Theme",
        "nl-NL": "Beach Theme",
        "it-IT": "Beach Theme",
        "pt-PT": "Beach Theme",
        "pt-BR": "Beach Theme",
        "es-ES": "Beach Theme",
        "es-MX": "Beach Theme",
        "ru-RU": "Beach Theme",
        "ko-KR": "Beach Theme",
        "zh-CN": "Beach Theme",
        "zh-TW": "Beach Theme"
      }
    },
    {
      "id": "678be02a-ccff-4c0e-b9ce-e97dd488b043",
      "name": {
        "en-US": "Underwater Theme",
        "ja-JP": "水中のテーマ",
        "en-GB": "Underwater Theme",
        "fr-FR": "Underwater Theme",
        "fr-CA": "Underwater Theme",
        "de-DE": "Underwater Theme",
        "nl-NL": "Underwater Theme",
        "it-IT": "Underwater Theme",
        "pt-PT": "Underwater Theme",
        "pt-BR": "Underwater Theme",
        "es-ES": "Underwater Theme",
        "es-MX": "Underwater Theme",
        "ru-RU": "Underwater Theme",
        "ko-KR": "Underwater Theme",
        "zh-CN": "Underwater Theme",
        "zh-TW": "Underwater Theme"
      }
    },
    {
      "id": "35fe7ea0-8bad-4727-87c7-e38703ae0fd8",
      "name": {
        "en-US": "Bonus Area",
        "ja-JP": "ボーナスエリア",
        "en-GB": "Bonus Area",
        "fr-FR": "Bonus Area",
        "fr-CA": "Bonus Area",
        "de-DE": "Bonus Area",
        "nl-NL": "Bonus Area",
        "it-IT": "Bonus Area",
        "pt-PT": "Bonus Area",
        "pt-BR": "Bonus Area",
        "es-ES": "Bonus Area",
        "es-MX": "Bonus Area",
        "ru-RU": "Bonus Area",
        "ko-KR": "Bonus Area",
        "zh-CN": "Bonus Area",
        "zh-TW": "Bonus Area"
      }
    },
    {
      "id": "7c608a9d-6d48-44e3-bc66-67d0f5f11e3d",
      "name": {
        "en-US": "World 4",
        "ja-JP": "WORLD 4 ",
        "en-GB": "World 4",
        "fr-FR": "World 4",
        "fr-CA": "World 4",
        "de-DE": "World 4",
        "nl-NL": "World 4",
        "it-IT": "World 4",
        "pt-PT": "World 4",
        "pt-BR": "World 4",
        "es-ES": "World 4",
        "es-MX": "World 4",
        "ru-RU": "World 4",
        "ko-KR": "World 4",
        "zh-CN": "World 4",
        "zh-TW": "World 4"
      }
    },
    {
      "id": "b138ce03-99d1-4daa-a53d-aae7c322f6fe",
      "name": {
        "en-US": "Ghost House Theme",
        "ja-JP": "おばけやしきのテーマ",
        "en-GB": "Ghost House Theme",
        "fr-FR": "Ghost House Theme",
        "fr-CA": "Ghost House Theme",
        "de-DE": "Ghost House Theme",
        "nl-NL": "Ghost House Theme",
        "it-IT": "Ghost House Theme",
        "pt-PT": "Ghost House Theme",
        "pt-BR": "Ghost House Theme",
        "es-ES": "Ghost House Theme",
        "es-MX": "Ghost House Theme",
        "ru-RU": "Ghost House Theme",
        "ko-KR": "Ghost House Theme",
        "zh-CN": "Ghost House Theme",
        "zh-TW": "Ghost House Theme"
      }
    },
    {
      "id": "a592e8b2-fd0d-4ce6-aa0f-dc56ee2e1286",
      "name": {
        "en-US": "Too Bad!",
        "ja-JP": "ミス",
        "en-GB": "Too Bad!",
        "fr-FR": "Too Bad!",
        "fr-CA": "Too Bad!",
        "de-DE": "Too Bad!",
        "nl-NL": "Too Bad!",
        "it-IT": "Too Bad!",
        "pt-PT": "Too Bad!",
        "pt-BR": "Too Bad!",
        "es-ES": "Too Bad!",
        "es-MX": "Too Bad!",
        "ru-RU": "Too Bad!",
        "ko-KR": "Too Bad!",
        "zh-CN": "Too Bad!",
        "zh-TW": "Too Bad!"
      }
    },
    {
      "id": "77f5cd67-8a98-416c-865c-2d92bd64323e",
      "name": {
        "en-US": "Game Over",
        "ja-JP": "ゲームオーバー",
        "en-GB": "Game Over",
        "fr-FR": "Game Over",
        "fr-CA": "Game Over",
        "de-DE": "Game Over",
        "nl-NL": "Game Over",
        "it-IT": "Game Over",
        "pt-PT": "Game Over",
        "pt-BR": "Game Over",
        "es-ES": "Game Over",
        "es-MX": "Game Over",
        "ru-RU": "Game Over",
        "ko-KR": "Game Over",
        "zh-CN": "Game Over",
        "zh-TW": "Game Over"
      }
    },
    {
      "id": "201e4f93-77be-4ffe-af10-b836be683cd1",
      "name": {
        "en-US": "Toad House Minigame",
        "ja-JP": "キノピオの家のミニゲーム",
        "en-GB": "Toad House Minigame",
        "fr-FR": "Toad House Minigame",
        "fr-CA": "Toad House Minigame",
        "de-DE": "Toad House Minigame",
        "nl-NL": "Toad House Minigame",
        "it-IT": "Toad House Minigame",
        "pt-PT": "Toad House Minigame",
        "pt-BR": "Toad House Minigame",
        "es-ES": "Toad House Minigame",
        "es-MX": "Toad House Minigame",
        "ru-RU": "Toad House Minigame",
        "ko-KR": "Toad House Minigame",
        "zh-CN": "Toad House Minigame",
        "zh-TW": "Toad House Minigame"
      }
    },
    {
      "id": "8dfc84a6-85ff-4a86-b054-46d6a00c03ba",
      "name": {
        "en-US": "Minigame Clear",
        "ja-JP": "ミニゲームクリア",
        "en-GB": "Minigame Clear",
        "fr-FR": "Minigame Clear",
        "fr-CA": "Minigame Clear",
        "de-DE": "Minigame Clear",
        "nl-NL": "Minigame Clear",
        "it-IT": "Minigame Clear",
        "pt-PT": "Minigame Clear",
        "pt-BR": "Minigame Clear",
        "es-ES": "Minigame Clear",
        "es-MX": "Minigame Clear",
        "ru-RU": "Minigame Clear",
        "ko-KR": "Minigame Clear",
        "zh-CN": "Minigame Clear",
        "zh-TW": "Minigame Clear"
      }
    },
    {
      "id": "8330c6e7-533f-4dc6-9069-8160712855cc",
      "name": {
        "en-US": "World 5",
        "ja-JP": "WORLD 5 ",
        "en-GB": "World 5",
        "fr-FR": "World 5",
        "fr-CA": "World 5",
        "de-DE": "World 5",
        "nl-NL": "World 5",
        "it-IT": "World 5",
        "pt-PT": "World 5",
        "pt-BR": "World 5",
        "es-ES": "World 5",
        "es-MX": "World 5",
        "ru-RU": "World 5",
        "ko-KR": "World 5",
        "zh-CN": "World 5",
        "zh-TW": "World 5"
      }
    },
    {
      "id": "1f9c58c9-c16f-4067-bc31-0e064256a86a",
      "name": {
        "en-US": "Tower Theme",
        "ja-JP": "塔のテーマ",
        "en-GB": "Tower Theme",
        "fr-FR": "Tower Theme",
        "fr-CA": "Tower Theme",
        "de-DE": "Tower Theme",
        "nl-NL": "Tower Theme",
        "it-IT": "Tower Theme",
        "pt-PT": "Tower Theme",
        "pt-BR": "Tower Theme",
        "es-ES": "Tower Theme",
        "es-MX": "Tower Theme",
        "ru-RU": "Tower Theme",
        "ko-KR": "Tower Theme",
        "zh-CN": "Tower Theme",
        "zh-TW": "Tower Theme"
      }
    },
    {
      "id": "b8d4e765-4a93-493f-8242-50cbf910ba44",
      "name": {
        "en-US": "Bowser Jr. Battle",
        "ja-JP": "クッパJr.戦",
        "en-GB": "Bowser Jr. Battle",
        "fr-FR": "Bowser Jr. Battle",
        "fr-CA": "Bowser Jr. Battle",
        "de-DE": "Bowser Jr. Battle",
        "nl-NL": "Bowser Jr. Battle",
        "it-IT": "Bowser Jr. Battle",
        "pt-PT": "Bowser Jr. Battle",
        "pt-BR": "Bowser Jr. Battle",
        "es-ES": "Bowser Jr. Battle",
        "es-MX": "Bowser Jr. Battle",
        "ru-RU": "Bowser Jr. Battle",
        "ko-KR": "Bowser Jr. Battle",
        "zh-CN": "Bowser Jr. Battle",
        "zh-TW": "Bowser Jr. Battle"
      }
    },
    {
      "id": "e5d29f6e-c959-4569-b15d-45f2daf341db",
      "name": {
        "en-US": "World 6",
        "ja-JP": "WORLD 6 ",
        "en-GB": "World 6",
        "fr-FR": "World 6",
        "fr-CA": "World 6",
        "de-DE": "World 6",
        "nl-NL": "World 6",
        "it-IT": "World 6",
        "pt-PT": "World 6",
        "pt-BR": "World 6",
        "es-ES": "World 6",
        "es-MX": "World 6",
        "ru-RU": "World 6",
        "ko-KR": "World 6",
        "zh-CN": "World 6",
        "zh-TW": "World 6"
      }
    },
    {
      "id": "794e4d8d-49e3-47be-9a5e-858a706097c4",
      "name": {
        "en-US": "Athletic Theme",
        "ja-JP": "アスレチックのテーマ",
        "en-GB": "Athletic Theme",
        "fr-FR": "Athletic Theme",
        "fr-CA": "Athletic Theme",
        "de-DE": "Athletic Theme",
        "nl-NL": "Athletic Theme",
        "it-IT": "Athletic Theme",
        "pt-PT": "Athletic Theme",
        "pt-BR": "Athletic Theme",
        "es-ES": "Athletic Theme",
        "es-MX": "Athletic Theme",
        "ru-RU": "Athletic Theme",
        "ko-KR": "Athletic Theme",
        "zh-CN": "Athletic Theme",
        "zh-TW": "Athletic Theme"
      }
    },
    {
      "id": "d38eb6f9-71b3-426e-a763-ecd270232cb0",
      "name": {
        "en-US": "Super Star",
        "ja-JP": "スター無敵",
        "en-GB": "Super Star",
        "fr-FR": "Super Star",
        "fr-CA": "Super Star",
        "de-DE": "Super Star",
        "nl-NL": "Super Star",
        "it-IT": "Super Star",
        "pt-PT": "Super Star",
        "pt-BR": "Super Star",
        "es-ES": "Super Star",
        "es-MX": "Super Star",
        "ru-RU": "Super Star",
        "ko-KR": "Super Star",
        "zh-CN": "Super Star",
        "zh-TW": "Super Star"
      }
    },
    {
      "id": "d27a143f-fd34-46e0-ae67-85d8b4c80907",
      "name": {
        "en-US": "World 7",
        "ja-JP": "WORLD 7 ",
        "en-GB": "World 7",
        "fr-FR": "World 7",
        "fr-CA": "World 7",
        "de-DE": "World 7",
        "nl-NL": "World 7",
        "it-IT": "World 7",
        "pt-PT": "World 7",
        "pt-BR": "World 7",
        "es-ES": "World 7",
        "es-MX": "World 7",
        "ru-RU": "World 7",
        "ko-KR": "World 7",
        "zh-CN": "World 7",
        "zh-TW": "World 7"
      }
    },
    {
      "id": "a60a3996-3ed1-461e-ba53-ba27a891fb68",
      "name": {
        "en-US": "Castle Theme",
        "ja-JP": "城のテーマ",
        "en-GB": "Castle Theme",
        "fr-FR": "Castle Theme",
        "fr-CA": "Castle Theme",
        "de-DE": "Castle Theme",
        "nl-NL": "Castle Theme",
        "it-IT": "Castle Theme",
        "pt-PT": "Castle Theme",
        "pt-BR": "Castle Theme",
        "es-ES": "Castle Theme",
        "es-MX": "Castle Theme",
        "ru-RU": "Castle Theme",
        "ko-KR": "Castle Theme",
        "zh-CN": "Castle Theme",
        "zh-TW": "Castle Theme"
      }
    },
    {
      "id": "3d19c59d-2416-48f5-b2fe-4db8fffb4b0d",
      "name": {
        "en-US": "Boss Battle",
        "ja-JP": "ボス戦",
        "en-GB": "Boss Battle",
        "fr-FR": "Boss Battle",
        "fr-CA": "Boss Battle",
        "de-DE": "Boss Battle",
        "nl-NL": "Boss Battle",
        "it-IT": "Boss Battle",
        "pt-PT": "Boss Battle",
        "pt-BR": "Boss Battle",
        "es-ES": "Boss Battle",
        "es-MX": "Boss Battle",
        "ru-RU": "Boss Battle",
        "ko-KR": "Boss Battle",
        "zh-CN": "Boss Battle",
        "zh-TW": "Boss Battle"
      }
    },
    {
      "id": "0d6a7a99-7f4b-4f67-83fa-9a5feab6c086",
      "name": {
        "en-US": "Boss Defeated",
        "ja-JP": "ボス撃破",
        "en-GB": "Boss Defeated",
        "fr-FR": "Boss Defeated",
        "fr-CA": "Boss Defeated",
        "de-DE": "Boss Defeated",
        "nl-NL": "Boss Defeated",
        "it-IT": "Boss Defeated",
        "pt-PT": "Boss Defeated",
        "pt-BR": "Boss Defeated",
        "es-ES": "Boss Defeated",
        "es-MX": "Boss Defeated",
        "ru-RU": "Boss Defeated",
        "ko-KR": "Boss Defeated",
        "zh-CN": "Boss Defeated",
        "zh-TW": "Boss Defeated"
      }
    },
    {
      "id": "5375c3da-0220-425e-8544-d7084f859caa",
      "name": {
        "en-US": "World 8",
        "ja-JP": "WORLD 8 ",
        "en-GB": "World 8",
        "fr-FR": "World 8",
        "fr-CA": "World 8",
        "de-DE": "World 8",
        "nl-NL": "World 8",
        "it-IT": "World 8",
        "pt-PT": "World 8",
        "pt-BR": "World 8",
        "es-ES": "World 8",
        "es-MX": "World 8",
        "ru-RU": "World 8",
        "ko-KR": "World 8",
        "zh-CN": "World 8",
        "zh-TW": "World 8"
      }
    },
    {
      "id": "ce0bad29-a175-4ea4-83a4-2ecb0678ddc6",
      "name": {
        "en-US": "Volcano Theme",
        "ja-JP": "火山のテーマ",
        "en-GB": "Volcano Theme",
        "fr-FR": "Volcano Theme",
        "fr-CA": "Volcano Theme",
        "de-DE": "Volcano Theme",
        "nl-NL": "Volcano Theme",
        "it-IT": "Volcano Theme",
        "pt-PT": "Volcano Theme",
        "pt-BR": "Volcano Theme",
        "es-ES": "Volcano Theme",
        "es-MX": "Volcano Theme",
        "ru-RU": "Volcano Theme",
        "ko-KR": "Volcano Theme",
        "zh-CN": "Volcano Theme",
        "zh-TW": "Volcano Theme"
      }
    },
    {
      "id": "a1469884-d171-4d0f-8f23-feb0448fed0d",
      "name": {
        "en-US": "Bowser Battle",
        "ja-JP": "クッパ戦",
        "en-GB": "Bowser Battle",
        "fr-FR": "Bowser Battle",
        "fr-CA": "Bowser Battle",
        "de-DE": "Bowser Battle",
        "nl-NL": "Bowser Battle",
        "it-IT": "Bowser Battle",
        "pt-PT": "Bowser Battle",
        "pt-BR": "Bowser Battle",
        "es-ES": "Bowser Battle",
        "es-MX": "Bowser Battle",
        "ru-RU": "Bowser Battle",
        "ko-KR": "Bowser Battle",
        "zh-CN": "Bowser Battle",
        "zh-TW": "Bowser Battle"
      }
    },
    {
      "id": "b13ea423-c212-42fe-8dbf-e3e9ae87b872",
      "name": {
        "en-US": "Bowser Defeated",
        "ja-JP": "クッパ撃破",
        "en-GB": "Bowser Defeated",
        "fr-FR": "Bowser Defeated",
        "fr-CA": "Bowser Defeated",
        "de-DE": "Bowser Defeated",
        "nl-NL": "Bowser Defeated",
        "it-IT": "Bowser Defeated",
        "pt-PT": "Bowser Defeated",
        "pt-BR": "Bowser Defeated",
        "es-ES": "Bowser Defeated",
        "es-MX": "Bowser Defeated",
        "ru-RU": "Bowser Defeated",
        "ko-KR": "Bowser Defeated",
        "zh-CN": "Bowser Defeated",
        "zh-TW": "Bowser Defeated"
      }
    },
    {
      "id": "f72eee7a-75f4-47ab-ba59-8c3b217fc69c",
      "name": {
        "en-US": "Princess Peach Rescued",
        "ja-JP": "ピーチ姫救出",
        "en-GB": "Princess Peach Rescued",
        "fr-FR": "Princess Peach Rescued",
        "fr-CA": "Princess Peach Rescued",
        "de-DE": "Princess Peach Rescued",
        "nl-NL": "Princess Peach Rescued",
        "it-IT": "Princess Peach Rescued",
        "pt-PT": "Princess Peach Rescued",
        "pt-BR": "Princess Peach Rescued",
        "es-ES": "Princess Peach Rescued",
        "es-MX": "Princess Peach Rescued",
        "ru-RU": "Princess Peach Rescued",
        "ko-KR": "Princess Peach Rescued",
        "zh-CN": "Princess Peach Rescued",
        "zh-TW": "Princess Peach Rescued"
      }
    },
    {
      "id": "1832ceb0-973d-45de-8f81-be36e3771ede",
      "name": {
        "en-US": "Staff Credits",
        "ja-JP": "スタッフクレジット",
        "en-GB": "Staff Credits",
        "fr-FR": "Staff Credits",
        "fr-CA": "Staff Credits",
        "de-DE": "Staff Credits",
        "nl-NL": "Staff Credits",
        "it-IT": "Staff Credits",
        "pt-PT": "Staff Credits",
        "pt-BR": "Staff Credits",
        "es-ES": "Staff Credits",
        "es-MX": "Staff Credits",
        "ru-RU": "Staff Credits",
        "ko-KR": "Staff Credits",
        "zh-CN": "Staff Credits",
        "zh-TW": "Staff Credits"
      }
    },
    {
      "id": "3860bbb2-456a-442b-8607-d1300c675bf9",
      "name": {
        "en-US": "Mario Vs. Luigi - Stage BGM 1",
        "ja-JP": "マリオVSルイージ ステージBGM 1",
        "en-GB": "Mario Vs. Luigi - Stage BGM 1",
        "fr-FR": "Mario Vs. Luigi - Stage BGM 1",
        "fr-CA": "Mario Vs. Luigi - Stage BGM 1",
        "de-DE": "Mario Vs. Luigi - Stage BGM 1",
        "nl-NL": "Mario Vs. Luigi - Stage BGM 1",
        "it-IT": "Mario Vs. Luigi - Stage BGM 1",
        "pt-PT": "Mario Vs. Luigi - Stage BGM 1",
        "pt-BR": "Mario Vs. Luigi - Stage BGM 1",
        "es-ES": "Mario Vs. Luigi - Stage BGM 1",
        "es-MX": "Mario Vs. Luigi - Stage BGM 1",
        "ru-RU": "Mario Vs. Luigi - Stage BGM 1",
        "ko-KR": "Mario Vs. Luigi - Stage BGM 1",
        "zh-CN": "Mario Vs. Luigi - Stage BGM 1",
        "zh-TW": "Mario Vs. Luigi - Stage BGM 1"
      }
    },
    {
      "id": "f460ef00-2430-46c3-9b6c-2be46ce3689e",
      "name": {
        "en-US": "Mario Vs. Luigi - Stage BGM 2",
        "ja-JP": "マリオVSルイージ ステージBGM 2",
        "en-GB": "Mario Vs. Luigi - Stage BGM 2",
        "fr-FR": "Mario Vs. Luigi - Stage BGM 2",
        "fr-CA": "Mario Vs. Luigi - Stage BGM 2",
        "de-DE": "Mario Vs. Luigi - Stage BGM 2",
        "nl-NL": "Mario Vs. Luigi - Stage BGM 2",
        "it-IT": "Mario Vs. Luigi - Stage BGM 2",
        "pt-PT": "Mario Vs. Luigi - Stage BGM 2",
        "pt-BR": "Mario Vs. Luigi - Stage BGM 2",
        "es-ES": "Mario Vs. Luigi - Stage BGM 2",
        "es-MX": "Mario Vs. Luigi - Stage BGM 2",
        "ru-RU": "Mario Vs. Luigi - Stage BGM 2",
        "ko-KR": "Mario Vs. Luigi - Stage BGM 2",
        "zh-CN": "Mario Vs. Luigi - Stage BGM 2",
        "zh-TW": "Mario Vs. Luigi - Stage BGM 2"
      }
    },
    {
      "id": "1eb872c5-e001-4c80-afc3-b76da31e0c72",
      "name": {
        "en-US": "Mario Vs. Luigi - Final Results (Win)",
        "ja-JP": "マリオVSルイージ 最終結果ジングル（勝ち）",
        "en-GB": "Mario Vs. Luigi - Final Results (Win)",
        "fr-FR": "Mario Vs. Luigi - Final Results (Win)",
        "fr-CA": "Mario Vs. Luigi - Final Results (Win)",
        "de-DE": "Mario Vs. Luigi - Final Results (Win)",
        "nl-NL": "Mario Vs. Luigi - Final Results (Win)",
        "it-IT": "Mario Vs. Luigi - Final Results (Win)",
        "pt-PT": "Mario Vs. Luigi - Final Results (Win)",
        "pt-BR": "Mario Vs. Luigi - Final Results (Win)",
        "es-ES": "Mario Vs. Luigi - Final Results (Win)",
        "es-MX": "Mario Vs. Luigi - Final Results (Win)",
        "ru-RU": "Mario Vs. Luigi - Final Results (Win)",
        "ko-KR": "Mario Vs. Luigi - Final Results (Win)",
        "zh-CN": "Mario Vs. Luigi - Final Results (Win)",
        "zh-TW": "Mario Vs. Luigi - Final Results (Win)"
      }
    },
    {
      "id": "8ad4338f-8070-45e0-837c-c6ee0f4a3f3e",
      "name": {
        "en-US": "Mario Vs. Luigi - Final Results (Lose)",
        "ja-JP": "マリオVSルイージ 最終結果ジングル（負け）",
        "en-GB": "Mario Vs. Luigi - Final Results (Lose)",
        "fr-FR": "Mario Vs. Luigi - Final Results (Lose)",
        "fr-CA": "Mario Vs. Luigi - Final Results (Lose)",
        "de-DE": "Mario Vs. Luigi - Final Results (Lose)",
        "nl-NL": "Mario Vs. Luigi - Final Results (Lose)",
        "it-IT": "Mario Vs. Luigi - Final Results (Lose)",
        "pt-PT": "Mario Vs. Luigi - Final Results (Lose)",
        "pt-BR": "Mario Vs. Luigi - Final Results (Lose)",
        "es-ES": "Mario Vs. Luigi - Final Results (Lose)",
        "es-MX": "Mario Vs. Luigi - Final Results (Lose)",
        "ru-RU": "Mario Vs. Luigi - Final Results (Lose)",
        "ko-KR": "Mario Vs. Luigi - Final Results (Lose)",
        "zh-CN": "Mario Vs. Luigi - Final Results (Lose)",
        "zh-TW": "Mario Vs. Luigi - Final Results (Lose)"
      }
    },
    {
      "id": "a00b21a8-9df3-4038-86f0-aef774da9d77",
      "name": {
        "en-US": "Mario Vs. Luigi - Final Results",
        "ja-JP": "マリオVSルイージ 最終結果",
        "en-GB": "Mario Vs. Luigi - Final Results",
        "fr-FR": "Mario Vs. Luigi - Final Results",
        "fr-CA": "Mario Vs. Luigi - Final Results",
        "de-DE": "Mario Vs. Luigi - Final Results",
        "nl-NL": "Mario Vs. Luigi - Final Results",
        "it-IT": "Mario Vs. Luigi - Final Results",
        "pt-PT": "Mario Vs. Luigi - Final Results",
        "pt-BR": "Mario Vs. Luigi - Final Results",
        "es-ES": "Mario Vs. Luigi - Final Results",
        "es-MX": "Mario Vs. Luigi - Final Results",
        "ru-RU": "Mario Vs. Luigi - Final Results",
        "ko-KR": "Mario Vs. Luigi - Final Results",
        "zh-CN": "Mario Vs. Luigi - Final Results",
        "zh-TW": "Mario Vs. Luigi - Final Results"
      }
    },
    {
      "id": "e4220385-2ffd-42c4-a8da-4b8fb380f308",
      "name": {
        "en-US": "Minigames: Main Menu",
        "ja-JP": "ミニゲーム：メインメニュー",
        "en-GB": "Minigames: Main Menu",
        "fr-FR": "Minigames: Main Menu",
        "fr-CA": "Minigames: Main Menu",
        "de-DE": "Minigames: Main Menu",
        "nl-NL": "Minigames: Main Menu",
        "it-IT": "Minigames: Main Menu",
        "pt-PT": "Minigames: Main Menu",
        "pt-BR": "Minigames: Main Menu",
        "es-ES": "Minigames: Main Menu",
        "es-MX": "Minigames: Main Menu",
        "ru-RU": "Minigames: Main Menu",
        "ko-KR": "Minigames: Main Menu",
        "zh-CN": "Minigames: Main Menu",
        "zh-TW": "Minigames: Main Menu"
      }
    },
    {
      "id": "2fef4aa8-063b-4fa1-8f12-bcf7bdebd2af",
      "name": {
        "en-US": "Minigames: Game Select",
        "ja-JP": "ミニゲーム：ゲーム選択",
        "en-GB": "Minigames: Game Select",
        "fr-FR": "Minigames: Game Select",
        "fr-CA": "Minigames: Game Select",
        "de-DE": "Minigames: Game Select",
        "nl-NL": "Minigames: Game Select",
        "it-IT": "Minigames: Game Select",
        "pt-PT": "Minigames: Game Select",
        "pt-BR": "Minigames: Game Select",
        "es-ES": "Minigames: Game Select",
        "es-MX": "Minigames: Game Select",
        "ru-RU": "Minigames: Game Select",
        "ko-KR": "Minigames: Game Select",
        "zh-CN": "Minigames: Game Select",
        "zh-TW": "Minigames: Game Select"
      }
    },
    {
      "id": "fe603b47-9245-4fc1-89e5-c55feb708f3b",
      "name": {
        "en-US": "Minigames: Game Explanation",
        "ja-JP": "ミニゲーム：ゲーム説明",
        "en-GB": "Minigames: Game Explanation",
        "fr-FR": "Minigames: Game Explanation",
        "fr-CA": "Minigames: Game Explanation",
        "de-DE": "Minigames: Game Explanation",
        "nl-NL": "Minigames: Game Explanation",
        "it-IT": "Minigames: Game Explanation",
        "pt-PT": "Minigames: Game Explanation",
        "pt-BR": "Minigames: Game Explanation",
        "es-ES": "Minigames: Game Explanation",
        "es-MX": "Minigames: Game Explanation",
        "ru-RU": "Minigames: Game Explanation",
        "ko-KR": "Minigames: Game Explanation",
        "zh-CN": "Minigames: Game Explanation",
        "zh-TW": "Minigames: Game Explanation"
      }
    },
    {
      "id": "e3263096-af06-44be-8c7b-e1e027f4a31a",
      "name": {
        "en-US": "Snowball Slalom",
        "ja-JP": "ゆきだるま ころがし",
        "en-GB": "Snowball Slalom",
        "fr-FR": "Snowball Slalom",
        "fr-CA": "Snowball Slalom",
        "de-DE": "Snowball Slalom",
        "nl-NL": "Snowball Slalom",
        "it-IT": "Snowball Slalom",
        "pt-PT": "Snowball Slalom",
        "pt-BR": "Snowball Slalom",
        "es-ES": "Snowball Slalom",
        "es-MX": "Snowball Slalom",
        "ru-RU": "Snowball Slalom",
        "ko-KR": "Snowball Slalom",
        "zh-CN": "Snowball Slalom",
        "zh-TW": "Snowball Slalom"
      }
    },
    {
      "id": "7e1870b0-81be-441f-872a-9f661042406e",
      "name": {
        "en-US": "Vs. Lakitu Launch",
        "ja-JP": "たまいれパチンコ",
        "en-GB": "Vs. Lakitu Launch",
        "fr-FR": "Vs. Lakitu Launch",
        "fr-CA": "Vs. Lakitu Launch",
        "de-DE": "Vs. Lakitu Launch",
        "nl-NL": "Vs. Lakitu Launch",
        "it-IT": "Vs. Lakitu Launch",
        "pt-PT": "Vs. Lakitu Launch",
        "pt-BR": "Vs. Lakitu Launch",
        "es-ES": "Vs. Lakitu Launch",
        "es-MX": "Vs. Lakitu Launch",
        "ru-RU": "Vs. Lakitu Launch",
        "ko-KR": "Vs. Lakitu Launch",
        "zh-CN": "Vs. Lakitu Launch",
        "zh-TW": "Vs. Lakitu Launch"
      }
    },
    {
      "id": "caf59f3e-b242-4d3a-84a0-80cb39ff090b",
      "name": {
        "en-US": "Run, Bob-omb, Run!",
        "ja-JP": "あやうし！ボムへい",
        "en-GB": "Run, Bob-omb, Run!",
        "fr-FR": "Run, Bob-omb, Run!",
        "fr-CA": "Run, Bob-omb, Run!",
        "de-DE": "Run, Bob-omb, Run!",
        "nl-NL": "Run, Bob-omb, Run!",
        "it-IT": "Run, Bob-omb, Run!",
        "pt-PT": "Run, Bob-omb, Run!",
        "pt-BR": "Run, Bob-omb, Run!",
        "es-ES": "Run, Bob-omb, Run!",
        "es-MX": "Run, Bob-omb, Run!",
        "ru-RU": "Run, Bob-omb, Run!",
        "ko-KR": "Run, Bob-omb, Run!",
        "zh-CN": "Run, Bob-omb, Run!",
        "zh-TW": "Run, Bob-omb, Run!"
      }
    },
    {
      "id": "97917620-1196-4ac5-82cc-c3777c131e41",
      "name": {
        "en-US": "Whack-a-Monty",
        "ja-JP": "ボコボコもぐらたたき",
        "en-GB": "Whack-a-Monty",
        "fr-FR": "Whack-a-Monty",
        "fr-CA": "Whack-a-Monty",
        "de-DE": "Whack-a-Monty",
        "nl-NL": "Whack-a-Monty",
        "it-IT": "Whack-a-Monty",
        "pt-PT": "Whack-a-Monty",
        "pt-BR": "Whack-a-Monty",
        "es-ES": "Whack-a-Monty",
        "es-MX": "Whack-a-Monty",
        "ru-RU": "Whack-a-Monty",
        "ko-KR": "Whack-a-Monty",
        "zh-CN": "Whack-a-Monty",
        "zh-TW": "Whack-a-Monty"
      }
    },
    {
      "id": "b1584421-822b-4d35-b4d0-23535be2b1f6",
      "name": {
        "en-US": "Balloon Racing",
        "ja-JP": "バルーン・レーシング",
        "en-GB": "Balloon Racing",
        "fr-FR": "Balloon Racing",
        "fr-CA": "Balloon Racing",
        "de-DE": "Balloon Racing",
        "nl-NL": "Balloon Racing",
        "it-IT": "Balloon Racing",
        "pt-PT": "Balloon Racing",
        "pt-BR": "Balloon Racing",
        "es-ES": "Balloon Racing",
        "es-MX": "Balloon Racing",
        "ru-RU": "Balloon Racing",
        "ko-KR": "Balloon Racing",
        "zh-CN": "Balloon Racing",
        "zh-TW": "Balloon Racing"
      }
    },
    {
      "id": "db89e125-ea1c-4225-b6f8-a28cc2d9be14",
      "name": {
        "en-US": "Wanted!",
        "ja-JP": "あいつをさがせ！",
        "en-GB": "Wanted!",
        "fr-FR": "Wanted!",
        "fr-CA": "Wanted!",
        "de-DE": "Wanted!",
        "nl-NL": "Wanted!",
        "it-IT": "Wanted!",
        "pt-PT": "Wanted!",
        "pt-BR": "Wanted!",
        "es-ES": "Wanted!",
        "es-MX": "Wanted!",
        "ru-RU": "Wanted!",
        "ko-KR": "Wanted!",
        "zh-CN": "Wanted!",
        "zh-TW": "Wanted!"
      }
    },
    {
      "id": "7f23d76b-747d-4133-bea7-2a7db8bebc5b",
      "name": {
        "en-US": "Which Wiggler?",
        "ja-JP": "ハナチャンをさがせ",
        "en-GB": "Which Wiggler?",
        "fr-FR": "Which Wiggler?",
        "fr-CA": "Which Wiggler?",
        "de-DE": "Which Wiggler?",
        "nl-NL": "Which Wiggler?",
        "it-IT": "Which Wiggler?",
        "pt-PT": "Which Wiggler?",
        "pt-BR": "Which Wiggler?",
        "es-ES": "Which Wiggler?",
        "es-MX": "Which Wiggler?",
        "ru-RU": "Which Wiggler?",
        "ko-KR": "Which Wiggler?",
        "zh-CN": "Which Wiggler?",
        "zh-TW": "Which Wiggler?"
      }
    },
    {
      "id": "2b208c81-3618-48e2-b0ec-31072eec6698",
      "name": {
        "en-US": "Puzzle Panel",
        "ja-JP": "パズルパネル",
        "en-GB": "Puzzle Panel",
        "fr-FR": "Puzzle Panel",
        "fr-CA": "Puzzle Panel",
        "de-DE": "Puzzle Panel",
        "nl-NL": "Puzzle Panel",
        "it-IT": "Puzzle Panel",
        "pt-PT": "Puzzle Panel",
        "pt-BR": "Puzzle Panel",
        "es-ES": "Puzzle Panel",
        "es-MX": "Puzzle Panel",
        "ru-RU": "Puzzle Panel",
        "ko-KR": "Puzzle Panel",
        "zh-CN": "Puzzle Panel",
        "zh-TW": "Puzzle Panel"
      }
    },
    {
      "id": "06c3a41d-89c6-4fd4-bafe-94fa56850031",
      "name": {
        "en-US": "Memory Match",
        "ja-JP": "ルイージのしんけいすいじゃく",
        "en-GB": "Memory Match",
        "fr-FR": "Memory Match",
        "fr-CA": "Memory Match",
        "de-DE": "Memory Match",
        "nl-NL": "Memory Match",
        "it-IT": "Memory Match",
        "pt-PT": "Memory Match",
        "pt-BR": "Memory Match",
        "es-ES": "Memory Match",
        "es-MX": "Memory Match",
        "ru-RU": "Memory Match",
        "ko-KR": "Memory Match",
        "zh-CN": "Memory Match",
        "zh-TW": "Memory Match"
      }
    },
    {
      "id": "79e532e8-76fa-450a-b8a4-340b0a94f83b",
      "name": {
        "en-US": "Sort or 'Splode",
        "ja-JP": "ボムへいをわけろ！",
        "en-GB": "Sort or 'Splode",
        "fr-FR": "Sort or 'Splode",
        "fr-CA": "Sort or 'Splode",
        "de-DE": "Sort or 'Splode",
        "nl-NL": "Sort or 'Splode",
        "it-IT": "Sort or 'Splode",
        "pt-PT": "Sort or 'Splode",
        "pt-BR": "Sort or 'Splode",
        "es-ES": "Sort or 'Splode",
        "es-MX": "Sort or 'Splode",
        "ru-RU": "Sort or 'Splode",
        "ko-KR": "Sort or 'Splode",
        "zh-CN": "Sort or 'Splode",
        "zh-TW": "Sort or 'Splode"
      }
    },
    {
      "id": "8022264d-7a27-4d28-a7cc-67f0830d7c79",
      "name": {
        "en-US": "Trampoline Time",
        "ja-JP": "トランポリンマリオ",
        "en-GB": "Trampoline Time",
        "fr-FR": "Trampoline Time",
        "fr-CA": "Trampoline Time",
        "de-DE": "Trampoline Time",
        "nl-NL": "Trampoline Time",
        "it-IT": "Trampoline Time",
        "pt-PT": "Trampoline Time",
        "pt-BR": "Trampoline Time",
        "es-ES": "Trampoline Time",
        "es-MX": "Trampoline Time",
        "ru-RU": "Trampoline Time",
        "ko-KR": "Trampoline Time",
        "zh-CN": "Trampoline Time",
        "zh-TW": "Trampoline Time"
      }
    },
    {
      "id": "d754cdb4-9181-4e5a-af35-c45895daccae",
      "name": {
        "en-US": "Loves Me...",
        "ja-JP": "どきどき！はなうらない",
        "en-GB": "Loves Me...",
        "fr-FR": "Loves Me...",
        "fr-CA": "Loves Me...",
        "de-DE": "Loves Me...",
        "nl-NL": "Loves Me...",
        "it-IT": "Loves Me...",
        "pt-PT": "Loves Me...",
        "pt-BR": "Loves Me...",
        "es-ES": "Loves Me...",
        "es-MX": "Loves Me...",
        "ru-RU": "Loves Me...",
        "ko-KR": "Loves Me...",
        "zh-CN": "Loves Me...",
        "zh-TW": "Loves Me..."
      }
    },
    {
      "id": "e5dab97f-634e-4c06-9c17-16e033df17ce",
      "name": {
        "en-US": "Bob-omb Reverse",
        "ja-JP": "ボムへい・リバーシ",
        "en-GB": "Bob-omb Reverse",
        "fr-FR": "Bob-omb Reverse",
        "fr-CA": "Bob-omb Reverse",
        "de-DE": "Bob-omb Reverse",
        "nl-NL": "Bob-omb Reverse",
        "it-IT": "Bob-omb Reverse",
        "pt-PT": "Bob-omb Reverse",
        "pt-BR": "Bob-omb Reverse",
        "es-ES": "Bob-omb Reverse",
        "es-MX": "Bob-omb Reverse",
        "ru-RU": "Bob-omb Reverse",
        "ko-KR": "Bob-omb Reverse",
        "zh-CN": "Bob-omb Reverse",
        "zh-TW": "Bob-omb Reverse"
      }
    },
    {
      "id": "65a5a9e6-38d8-4015-8b49-5fa16cc2d8eb",
      "name": {
        "en-US": "Minigames: Vs. Battle - Final Results",
        "ja-JP": "ミニゲーム：VSバトル 最終結果",
        "en-GB": "Minigames: Vs. Battle - Final Results",
        "fr-FR": "Minigames: Vs. Battle - Final Results",
        "fr-CA": "Minigames: Vs. Battle - Final Results",
        "de-DE": "Minigames: Vs. Battle - Final Results",
        "nl-NL": "Minigames: Vs. Battle - Final Results",
        "it-IT": "Minigames: Vs. Battle - Final Results",
        "pt-PT": "Minigames: Vs. Battle - Final Results",
        "pt-BR": "Minigames: Vs. Battle - Final Results",
        "es-ES": "Minigames: Vs. Battle - Final Results",
        "es-MX": "Minigames: Vs. Battle - Final Results",
        "ru-RU": "Minigames: Vs. Battle - Final Results",
        "ko-KR": "Minigames: Vs. Battle - Final Results",
        "zh-CN": "Minigames: Vs. Battle - Final Results",
        "zh-TW": "Minigames: Vs. Battle - Final Results"
      }
    }
  ],
  "localesWithDistinctTrackNames": [
    "en-US",
    "ja-JP"
  ],
  "localesWithDistinctTrackNamesCount": 2
}