{
  "nameEnUS": "New Super Mario Bros. U Deluxe",
  "id": "96074b69-9403-46b1-ac53-9d9553d73f9f",
  "hardware": "Nintendo Switch",
  "timestamp": 1751331600,
  "name": {
    "en-US": "New Super Mario Bros. U Deluxe",
    "ja-JP": "New スーパーマリオブラザーズ U デラックス",
    "en-GB": "New Super Mario Bros. U Deluxe",
    "fr-FR": "New Super Mario Bros. U Deluxe",
    "fr-CA": "New Super Mario Bros. U Deluxe",
    "de-DE": "New Super Mario Bros. U Deluxe",
    "nl-NL": "New Super Mario Bros. U Deluxe",
    "it-IT": "New Super Mario Bros. U Deluxe",
    "pt-PT": "New Super Mario Bros. U Deluxe",
    "pt-BR": "New Super Mario Bros. U Deluxe",
    "es-ES": "New Super Mario Bros. U Deluxe",
    "es-MX": "New Super Mario Bros. U Deluxe",
    "ru-RU": "New Super Mario Bros. U Deluxe",
    "ko-KR": "뉴 슈퍼 마리오브라더스 U 디럭스",
    "zh-CN": "New 超级马力欧兄弟U 豪华版",
    "zh-TW": "New 超級瑪利歐兄弟U 豪華版"
  },
  "allTracksPlaylistId": "94959d52-c412-4a3c-9651-aa1e55e299df",
  "tracks": [
    {
      "id": "254cb7a5-eac4-4b92-8381-f21c970a6fc2",
      "name": {
        "en-US": "Title",
        "ja-JP": "タイトル",
        "en-GB": "Title",
        "fr-FR": "Title",
        "fr-CA": "Title",
        "de-DE": "Title",
        "nl-NL": "Title",
        "it-IT": "Title",
        "pt-PT": "Title",
        "pt-BR": "Title",
        "es-ES": "Title",
        "es-MX": "Title",
        "ru-RU": "Title",
        "ko-KR": "Title",
        "zh-CN": "Title",
        "zh-TW": "Title"
      }
    },
    {
      "id": "f422d994-d314-4b08-bdcd-a4a1f0b2b922",
      "name": {
        "en-US": "File Select",
        "ja-JP": "ファイルセレクト",
        "en-GB": "File Select",
        "fr-FR": "File Select",
        "fr-CA": "File Select",
        "de-DE": "File Select",
        "nl-NL": "File Select",
        "it-IT": "File Select",
        "pt-PT": "File Select",
        "pt-BR": "File Select",
        "es-ES": "File Select",
        "es-MX": "File Select",
        "ru-RU": "File Select",
        "ko-KR": "File Select",
        "zh-CN": "File Select",
        "zh-TW": "File Select"
      }
    },
    {
      "id": "6649c054-d45a-430e-b963-e29ffbaa0872",
      "name": {
        "en-US": "Prologue",
        "ja-JP": "プロローグ",
        "en-GB": "Prologue",
        "fr-FR": "Prologue",
        "fr-CA": "Prologue",
        "de-DE": "Prologue",
        "nl-NL": "Prologue",
        "it-IT": "Prologue",
        "pt-PT": "Prologue",
        "pt-BR": "Prologue",
        "es-ES": "Prologue",
        "es-MX": "Prologue",
        "ru-RU": "Prologue",
        "ko-KR": "Prologue",
        "zh-CN": "Prologue",
        "zh-TW": "Prologue"
      }
    },
    {
      "id": "e5b5d7eb-7da3-45e7-b4ec-ae538ad26907",
      "name": {
        "en-US": "World: Acorn Plains",
        "ja-JP": "ワールド：ドングリへいげん",
        "en-GB": "World: Acorn Plains",
        "fr-FR": "World: Acorn Plains",
        "fr-CA": "World: Acorn Plains",
        "de-DE": "World: Acorn Plains",
        "nl-NL": "World: Acorn Plains",
        "it-IT": "World: Acorn Plains",
        "pt-PT": "World: Acorn Plains",
        "pt-BR": "World: Acorn Plains",
        "es-ES": "World: Acorn Plains",
        "es-MX": "World: Acorn Plains",
        "ru-RU": "World: Acorn Plains",
        "ko-KR": "World: Acorn Plains",
        "zh-CN": "World: Acorn Plains",
        "zh-TW": "World: Acorn Plains"
      }
    },
    {
      "id": "1838c1e2-e914-40e3-b58e-cc22bd9c9b1b",
      "name": {
        "en-US": "Ground Theme",
        "ja-JP": "地上のテーマ",
        "en-GB": "Ground Theme",
        "fr-FR": "Ground Theme",
        "fr-CA": "Ground Theme",
        "de-DE": "Ground Theme",
        "nl-NL": "Ground Theme",
        "it-IT": "Ground Theme",
        "pt-PT": "Ground Theme",
        "pt-BR": "Ground Theme",
        "es-ES": "Ground Theme",
        "es-MX": "Ground Theme",
        "ru-RU": "Ground Theme",
        "ko-KR": "Ground Theme",
        "zh-CN": "Ground Theme",
        "zh-TW": "Ground Theme"
      }
    },
    {
      "id": "d0c80813-80b0-4eb2-bd94-5b6a5c391d68",
      "name": {
        "en-US": "Hurry Up!",
        "ja-JP": "ハリーアップ",
        "en-GB": "Hurry Up!",
        "fr-FR": "Hurry Up!",
        "fr-CA": "Hurry Up!",
        "de-DE": "Hurry Up!",
        "nl-NL": "Hurry Up!",
        "it-IT": "Hurry Up!",
        "pt-PT": "Hurry Up!",
        "pt-BR": "Hurry Up!",
        "es-ES": "Hurry Up!",
        "es-MX": "Hurry Up!",
        "ru-RU": "Hurry Up!",
        "ko-KR": "Hurry Up!",
        "zh-CN": "Hurry Up!",
        "zh-TW": "Hurry Up!"
      }
    },
    {
      "id": "6412641d-d22e-4e50-a509-15699af4bf18",
      "name": {
        "en-US": "Ground Theme (Hurry Up!)",
        "ja-JP": "地上のテーマ（ハリーアップ）",
        "en-GB": "Ground Theme (Hurry Up!)",
        "fr-FR": "Ground Theme (Hurry Up!)",
        "fr-CA": "Ground Theme (Hurry Up!)",
        "de-DE": "Ground Theme (Hurry Up!)",
        "nl-NL": "Ground Theme (Hurry Up!)",
        "it-IT": "Ground Theme (Hurry Up!)",
        "pt-PT": "Ground Theme (Hurry Up!)",
        "pt-BR": "Ground Theme (Hurry Up!)",
        "es-ES": "Ground Theme (Hurry Up!)",
        "es-MX": "Ground Theme (Hurry Up!)",
        "ru-RU": "Ground Theme (Hurry Up!)",
        "ko-KR": "Ground Theme (Hurry Up!)",
        "zh-CN": "Ground Theme (Hurry Up!)",
        "zh-TW": "Ground Theme (Hurry Up!)"
      }
    },
    {
      "id": "b253e78a-895f-475c-845e-5d525fe9dd36",
      "name": {
        "en-US": "Ground Theme (Baby Yoshi)",
        "ja-JP": "地上のテーマ（ちびヨッシー）",
        "en-GB": "Ground Theme (Baby Yoshi)",
        "fr-FR": "Ground Theme (Baby Yoshi)",
        "fr-CA": "Ground Theme (Baby Yoshi)",
        "de-DE": "Ground Theme (Baby Yoshi)",
        "nl-NL": "Ground Theme (Baby Yoshi)",
        "it-IT": "Ground Theme (Baby Yoshi)",
        "pt-PT": "Ground Theme (Baby Yoshi)",
        "pt-BR": "Ground Theme (Baby Yoshi)",
        "es-ES": "Ground Theme (Baby Yoshi)",
        "es-MX": "Ground Theme (Baby Yoshi)",
        "ru-RU": "Ground Theme (Baby Yoshi)",
        "ko-KR": "Ground Theme (Baby Yoshi)",
        "zh-CN": "Ground Theme (Baby Yoshi)",
        "zh-TW": "Ground Theme (Baby Yoshi)"
      }
    },
    {
      "id": "e5128122-bdbb-4bd5-a06f-ace1c3ec5652",
      "name": {
        "en-US": "Course Clear",
        "ja-JP": "コースクリア",
        "en-GB": "Course Clear",
        "fr-FR": "Course Clear",
        "fr-CA": "Course Clear",
        "de-DE": "Course Clear",
        "nl-NL": "Course Clear",
        "it-IT": "Course Clear",
        "pt-PT": "Course Clear",
        "pt-BR": "Course Clear",
        "es-ES": "Course Clear",
        "es-MX": "Course Clear",
        "ru-RU": "Course Clear",
        "ko-KR": "Course Clear",
        "zh-CN": "Course Clear",
        "zh-TW": "Course Clear"
      }
    },
    {
      "id": "d6de566f-494e-45d8-b582-394185b1a44d",
      "name": {
        "en-US": "Underground Theme",
        "ja-JP": "地下のテーマ",
        "en-GB": "Underground Theme",
        "fr-FR": "Underground Theme",
        "fr-CA": "Underground Theme",
        "de-DE": "Underground Theme",
        "nl-NL": "Underground Theme",
        "it-IT": "Underground Theme",
        "pt-PT": "Underground Theme",
        "pt-BR": "Underground Theme",
        "es-ES": "Underground Theme",
        "es-MX": "Underground Theme",
        "ru-RU": "Underground Theme",
        "ko-KR": "Underground Theme",
        "zh-CN": "Underground Theme",
        "zh-TW": "Underground Theme"
      }
    },
    {
      "id": "23bd4b4b-04ae-49bf-8bfe-80eb8c9337f3",
      "name": {
        "en-US": "Underground Theme (Hurry Up!)",
        "ja-JP": "地下のテーマ（ハリーアップ）",
        "en-GB": "Underground Theme (Hurry Up!)",
        "fr-FR": "Underground Theme (Hurry Up!)",
        "fr-CA": "Underground Theme (Hurry Up!)",
        "de-DE": "Underground Theme (Hurry Up!)",
        "nl-NL": "Underground Theme (Hurry Up!)",
        "it-IT": "Underground Theme (Hurry Up!)",
        "pt-PT": "Underground Theme (Hurry Up!)",
        "pt-BR": "Underground Theme (Hurry Up!)",
        "es-ES": "Underground Theme (Hurry Up!)",
        "es-MX": "Underground Theme (Hurry Up!)",
        "ru-RU": "Underground Theme (Hurry Up!)",
        "ko-KR": "Underground Theme (Hurry Up!)",
        "zh-CN": "Underground Theme (Hurry Up!)",
        "zh-TW": "Underground Theme (Hurry Up!)"
      }
    },
    {
      "id": "2bc4da33-8c9a-43e3-8ec1-c25655aad85c",
      "name": {
        "en-US": "Underground Theme (Baby Yoshi)",
        "ja-JP": "地下のテーマ（ちびヨッシー）",
        "en-GB": "Underground Theme (Baby Yoshi)",
        "fr-FR": "Underground Theme (Baby Yoshi)",
        "fr-CA": "Underground Theme (Baby Yoshi)",
        "de-DE": "Underground Theme (Baby Yoshi)",
        "nl-NL": "Underground Theme (Baby Yoshi)",
        "it-IT": "Underground Theme (Baby Yoshi)",
        "pt-PT": "Underground Theme (Baby Yoshi)",
        "pt-BR": "Underground Theme (Baby Yoshi)",
        "es-ES": "Underground Theme (Baby Yoshi)",
        "es-MX": "Underground Theme (Baby Yoshi)",
        "ru-RU": "Underground Theme (Baby Yoshi)",
        "ko-KR": "Underground Theme (Baby Yoshi)",
        "zh-CN": "Underground Theme (Baby Yoshi)",
        "zh-TW": "Underground Theme (Baby Yoshi)"
      }
    },
    {
      "id": "acc81bf2-6f9d-4880-bc28-432305ce4501",
      "name": {
        "en-US": "Sudden Encounter",
        "ja-JP": "そうぐう戦",
        "en-GB": "Sudden Encounter",
        "fr-FR": "Sudden Encounter",
        "fr-CA": "Sudden Encounter",
        "de-DE": "Sudden Encounter",
        "nl-NL": "Sudden Encounter",
        "it-IT": "Sudden Encounter",
        "pt-PT": "Sudden Encounter",
        "pt-BR": "Sudden Encounter",
        "es-ES": "Sudden Encounter",
        "es-MX": "Sudden Encounter",
        "ru-RU": "Sudden Encounter",
        "ko-KR": "Sudden Encounter",
        "zh-CN": "Sudden Encounter",
        "zh-TW": "Sudden Encounter"
      }
    },
    {
      "id": "6ea1aec4-770c-40a1-a95b-b5928d8fb316",
      "name": {
        "en-US": "World: Layer-Cake Desert",
        "ja-JP": "ワールド：デザートさばく",
        "en-GB": "World: Layer-Cake Desert",
        "fr-FR": "World: Layer-Cake Desert",
        "fr-CA": "World: Layer-Cake Desert",
        "de-DE": "World: Layer-Cake Desert",
        "nl-NL": "World: Layer-Cake Desert",
        "it-IT": "World: Layer-Cake Desert",
        "pt-PT": "World: Layer-Cake Desert",
        "pt-BR": "World: Layer-Cake Desert",
        "es-ES": "World: Layer-Cake Desert",
        "es-MX": "World: Layer-Cake Desert",
        "ru-RU": "World: Layer-Cake Desert",
        "ko-KR": "World: Layer-Cake Desert",
        "zh-CN": "World: Layer-Cake Desert",
        "zh-TW": "World: Layer-Cake Desert"
      }
    },
    {
      "id": "9a783b94-98d2-41eb-a4fa-994a9ec04935",
      "name": {
        "en-US": "Desert Theme",
        "ja-JP": "砂漠のテーマ",
        "en-GB": "Desert Theme",
        "fr-FR": "Desert Theme",
        "fr-CA": "Desert Theme",
        "de-DE": "Desert Theme",
        "nl-NL": "Desert Theme",
        "it-IT": "Desert Theme",
        "pt-PT": "Desert Theme",
        "pt-BR": "Desert Theme",
        "es-ES": "Desert Theme",
        "es-MX": "Desert Theme",
        "ru-RU": "Desert Theme",
        "ko-KR": "Desert Theme",
        "zh-CN": "Desert Theme",
        "zh-TW": "Desert Theme"
      }
    },
    {
      "id": "6c22c705-a56e-49e5-9c9e-20ff388f9eef",
      "name": {
        "en-US": "Desert Theme (Hurry Up!)",
        "ja-JP": "砂漠のテーマ（ハリーアップ）",
        "en-GB": "Desert Theme (Hurry Up!)",
        "fr-FR": "Desert Theme (Hurry Up!)",
        "fr-CA": "Desert Theme (Hurry Up!)",
        "de-DE": "Desert Theme (Hurry Up!)",
        "nl-NL": "Desert Theme (Hurry Up!)",
        "it-IT": "Desert Theme (Hurry Up!)",
        "pt-PT": "Desert Theme (Hurry Up!)",
        "pt-BR": "Desert Theme (Hurry Up!)",
        "es-ES": "Desert Theme (Hurry Up!)",
        "es-MX": "Desert Theme (Hurry Up!)",
        "ru-RU": "Desert Theme (Hurry Up!)",
        "ko-KR": "Desert Theme (Hurry Up!)",
        "zh-CN": "Desert Theme (Hurry Up!)",
        "zh-TW": "Desert Theme (Hurry Up!)"
      }
    },
    {
      "id": "c04f651a-07dc-4e50-9f8d-a263ae879c21",
      "name": {
        "en-US": "Desert Theme (Baby Yoshi)",
        "ja-JP": "砂漠のテーマ（ちびヨッシー）",
        "en-GB": "Desert Theme (Baby Yoshi)",
        "fr-FR": "Desert Theme (Baby Yoshi)",
        "fr-CA": "Desert Theme (Baby Yoshi)",
        "de-DE": "Desert Theme (Baby Yoshi)",
        "nl-NL": "Desert Theme (Baby Yoshi)",
        "it-IT": "Desert Theme (Baby Yoshi)",
        "pt-PT": "Desert Theme (Baby Yoshi)",
        "pt-BR": "Desert Theme (Baby Yoshi)",
        "es-ES": "Desert Theme (Baby Yoshi)",
        "es-MX": "Desert Theme (Baby Yoshi)",
        "ru-RU": "Desert Theme (Baby Yoshi)",
        "ko-KR": "Desert Theme (Baby Yoshi)",
        "zh-CN": "Desert Theme (Baby Yoshi)",
        "zh-TW": "Desert Theme (Baby Yoshi)"
      }
    },
    {
      "id": "a0c27f51-9e82-42b7-b923-2ef5cce8fe90",
      "name": {
        "en-US": "Toad House Minigame",
        "ja-JP": "キノピオの家のミニゲーム",
        "en-GB": "Toad House Minigame",
        "fr-FR": "Toad House Minigame",
        "fr-CA": "Toad House Minigame",
        "de-DE": "Toad House Minigame",
        "nl-NL": "Toad House Minigame",
        "it-IT": "Toad House Minigame",
        "pt-PT": "Toad House Minigame",
        "pt-BR": "Toad House Minigame",
        "es-ES": "Toad House Minigame",
        "es-MX": "Toad House Minigame",
        "ru-RU": "Toad House Minigame",
        "ko-KR": "Toad House Minigame",
        "zh-CN": "Toad House Minigame",
        "zh-TW": "Toad House Minigame"
      }
    },
    {
      "id": "5e97ec44-1d55-40f0-994f-3844860f500b",
      "name": {
        "en-US": "Fortress Theme",
        "ja-JP": "砦のテーマ",
        "en-GB": "Fortress Theme",
        "fr-FR": "Fortress Theme",
        "fr-CA": "Fortress Theme",
        "de-DE": "Fortress Theme",
        "nl-NL": "Fortress Theme",
        "it-IT": "Fortress Theme",
        "pt-PT": "Fortress Theme",
        "pt-BR": "Fortress Theme",
        "es-ES": "Fortress Theme",
        "es-MX": "Fortress Theme",
        "ru-RU": "Fortress Theme",
        "ko-KR": "Fortress Theme",
        "zh-CN": "Fortress Theme",
        "zh-TW": "Fortress Theme"
      }
    },
    {
      "id": "d75c8d22-143a-4154-b10f-c75875d5eb1e",
      "name": {
        "en-US": "Fortress Theme (Hurry Up!)",
        "ja-JP": "砦のテーマ（ハリーアップ）",
        "en-GB": "Fortress Theme (Hurry Up!)",
        "fr-FR": "Fortress Theme (Hurry Up!)",
        "fr-CA": "Fortress Theme (Hurry Up!)",
        "de-DE": "Fortress Theme (Hurry Up!)",
        "nl-NL": "Fortress Theme (Hurry Up!)",
        "it-IT": "Fortress Theme (Hurry Up!)",
        "pt-PT": "Fortress Theme (Hurry Up!)",
        "pt-BR": "Fortress Theme (Hurry Up!)",
        "es-ES": "Fortress Theme (Hurry Up!)",
        "es-MX": "Fortress Theme (Hurry Up!)",
        "ru-RU": "Fortress Theme (Hurry Up!)",
        "ko-KR": "Fortress Theme (Hurry Up!)",
        "zh-CN": "Fortress Theme (Hurry Up!)",
        "zh-TW": "Fortress Theme (Hurry Up!)"
      }
    },
    {
      "id": "2bd6718d-32fa-4a7f-975f-535bd7d89e6f",
      "name": {
        "en-US": "Boom Boom Battle",
        "ja-JP": "ブンブン戦",
        "en-GB": "Boom Boom Battle",
        "fr-FR": "Boom Boom Battle",
        "fr-CA": "Boom Boom Battle",
        "de-DE": "Boom Boom Battle",
        "nl-NL": "Boom Boom Battle",
        "it-IT": "Boom Boom Battle",
        "pt-PT": "Boom Boom Battle",
        "pt-BR": "Boom Boom Battle",
        "es-ES": "Boom Boom Battle",
        "es-MX": "Boom Boom Battle",
        "ru-RU": "Boom Boom Battle",
        "ko-KR": "Boom Boom Battle",
        "zh-CN": "Boom Boom Battle",
        "zh-TW": "Boom Boom Battle"
      }
    },
    {
      "id": "0350bf36-1554-4dbe-9873-98dd8b79e64c",
      "name": {
        "en-US": "Boom Boom Battle (Hurry Up!)",
        "ja-JP": "ブンブン戦（ハリーアップ）",
        "en-GB": "Boom Boom Battle (Hurry Up!)",
        "fr-FR": "Boom Boom Battle (Hurry Up!)",
        "fr-CA": "Boom Boom Battle (Hurry Up!)",
        "de-DE": "Boom Boom Battle (Hurry Up!)",
        "nl-NL": "Boom Boom Battle (Hurry Up!)",
        "it-IT": "Boom Boom Battle (Hurry Up!)",
        "pt-PT": "Boom Boom Battle (Hurry Up!)",
        "pt-BR": "Boom Boom Battle (Hurry Up!)",
        "es-ES": "Boom Boom Battle (Hurry Up!)",
        "es-MX": "Boom Boom Battle (Hurry Up!)",
        "ru-RU": "Boom Boom Battle (Hurry Up!)",
        "ko-KR": "Boom Boom Battle (Hurry Up!)",
        "zh-CN": "Boom Boom Battle (Hurry Up!)",
        "zh-TW": "Boom Boom Battle (Hurry Up!)"
      }
    },
    {
      "id": "a27b30e4-7b74-4b77-ba7d-f52d3cd0f245",
      "name": {
        "en-US": "Boss Clear",
        "ja-JP": "ボスクリア",
        "en-GB": "Boss Clear",
        "fr-FR": "Boss Clear",
        "fr-CA": "Boss Clear",
        "de-DE": "Boss Clear",
        "nl-NL": "Boss Clear",
        "it-IT": "Boss Clear",
        "pt-PT": "Boss Clear",
        "pt-BR": "Boss Clear",
        "es-ES": "Boss Clear",
        "es-MX": "Boss Clear",
        "ru-RU": "Boss Clear",
        "ko-KR": "Boss Clear",
        "zh-CN": "Boss Clear",
        "zh-TW": "Boss Clear"
      }
    },
    {
      "id": "b8353b51-1108-4e66-a08d-435230d6b398",
      "name": {
        "en-US": "World: Sparkling Waters",
        "ja-JP": "ワールド：ミントしょとう",
        "en-GB": "World: Sparkling Waters",
        "fr-FR": "World: Sparkling Waters",
        "fr-CA": "World: Sparkling Waters",
        "de-DE": "World: Sparkling Waters",
        "nl-NL": "World: Sparkling Waters",
        "it-IT": "World: Sparkling Waters",
        "pt-PT": "World: Sparkling Waters",
        "pt-BR": "World: Sparkling Waters",
        "es-ES": "World: Sparkling Waters",
        "es-MX": "World: Sparkling Waters",
        "ru-RU": "World: Sparkling Waters",
        "ko-KR": "World: Sparkling Waters",
        "zh-CN": "World: Sparkling Waters",
        "zh-TW": "World: Sparkling Waters"
      }
    },
    {
      "id": "dc787871-ef90-433e-97d8-cfb7b2144a4d",
      "name": {
        "en-US": "Coast Theme",
        "ja-JP": "海岸のテーマ",
        "en-GB": "Coast Theme",
        "fr-FR": "Coast Theme",
        "fr-CA": "Coast Theme",
        "de-DE": "Coast Theme",
        "nl-NL": "Coast Theme",
        "it-IT": "Coast Theme",
        "pt-PT": "Coast Theme",
        "pt-BR": "Coast Theme",
        "es-ES": "Coast Theme",
        "es-MX": "Coast Theme",
        "ru-RU": "Coast Theme",
        "ko-KR": "Coast Theme",
        "zh-CN": "Coast Theme",
        "zh-TW": "Coast Theme"
      }
    },
    {
      "id": "6705f1fa-bc2e-4200-b284-c32c015abd97",
      "name": {
        "en-US": "Coast Theme (Hurry Up!)",
        "ja-JP": "海岸のテーマ（ハリーアップ）",
        "en-GB": "Coast Theme (Hurry Up!)",
        "fr-FR": "Coast Theme (Hurry Up!)",
        "fr-CA": "Coast Theme (Hurry Up!)",
        "de-DE": "Coast Theme (Hurry Up!)",
        "nl-NL": "Coast Theme (Hurry Up!)",
        "it-IT": "Coast Theme (Hurry Up!)",
        "pt-PT": "Coast Theme (Hurry Up!)",
        "pt-BR": "Coast Theme (Hurry Up!)",
        "es-ES": "Coast Theme (Hurry Up!)",
        "es-MX": "Coast Theme (Hurry Up!)",
        "ru-RU": "Coast Theme (Hurry Up!)",
        "ko-KR": "Coast Theme (Hurry Up!)",
        "zh-CN": "Coast Theme (Hurry Up!)",
        "zh-TW": "Coast Theme (Hurry Up!)"
      }
    },
    {
      "id": "a979d275-c2b1-4300-bea9-69781b12df16",
      "name": {
        "en-US": "Coast Theme (Baby Yoshi)",
        "ja-JP": "海岸のテーマ（ちびヨッシー）",
        "en-GB": "Coast Theme (Baby Yoshi)",
        "fr-FR": "Coast Theme (Baby Yoshi)",
        "fr-CA": "Coast Theme (Baby Yoshi)",
        "de-DE": "Coast Theme (Baby Yoshi)",
        "nl-NL": "Coast Theme (Baby Yoshi)",
        "it-IT": "Coast Theme (Baby Yoshi)",
        "pt-PT": "Coast Theme (Baby Yoshi)",
        "pt-BR": "Coast Theme (Baby Yoshi)",
        "es-ES": "Coast Theme (Baby Yoshi)",
        "es-MX": "Coast Theme (Baby Yoshi)",
        "ru-RU": "Coast Theme (Baby Yoshi)",
        "ko-KR": "Coast Theme (Baby Yoshi)",
        "zh-CN": "Coast Theme (Baby Yoshi)",
        "zh-TW": "Coast Theme (Baby Yoshi)"
      }
    },
    {
      "id": "f56ee882-9ce3-4162-b132-9606aa9e3169",
      "name": {
        "en-US": "Underwater Theme",
        "ja-JP": "水中のテーマ",
        "en-GB": "Underwater Theme",
        "fr-FR": "Underwater Theme",
        "fr-CA": "Underwater Theme",
        "de-DE": "Underwater Theme",
        "nl-NL": "Underwater Theme",
        "it-IT": "Underwater Theme",
        "pt-PT": "Underwater Theme",
        "pt-BR": "Underwater Theme",
        "es-ES": "Underwater Theme",
        "es-MX": "Underwater Theme",
        "ru-RU": "Underwater Theme",
        "ko-KR": "Underwater Theme",
        "zh-CN": "Underwater Theme",
        "zh-TW": "Underwater Theme"
      }
    },
    {
      "id": "8a8df46d-0487-4a47-b12a-8e9affad51f6",
      "name": {
        "en-US": "Underwater Theme (Hurry Up!)",
        "ja-JP": "水中のテーマ（ハリーアップ）",
        "en-GB": "Underwater Theme (Hurry Up!)",
        "fr-FR": "Underwater Theme (Hurry Up!)",
        "fr-CA": "Underwater Theme (Hurry Up!)",
        "de-DE": "Underwater Theme (Hurry Up!)",
        "nl-NL": "Underwater Theme (Hurry Up!)",
        "it-IT": "Underwater Theme (Hurry Up!)",
        "pt-PT": "Underwater Theme (Hurry Up!)",
        "pt-BR": "Underwater Theme (Hurry Up!)",
        "es-ES": "Underwater Theme (Hurry Up!)",
        "es-MX": "Underwater Theme (Hurry Up!)",
        "ru-RU": "Underwater Theme (Hurry Up!)",
        "ko-KR": "Underwater Theme (Hurry Up!)",
        "zh-CN": "Underwater Theme (Hurry Up!)",
        "zh-TW": "Underwater Theme (Hurry Up!)"
      }
    },
    {
      "id": "c8e7a8f8-4f48-4a37-935c-bd108500812a",
      "name": {
        "en-US": "Underwater Theme (Baby Yoshi)",
        "ja-JP": "水中のテーマ（ちびヨッシー）",
        "en-GB": "Underwater Theme (Baby Yoshi)",
        "fr-FR": "Underwater Theme (Baby Yoshi)",
        "fr-CA": "Underwater Theme (Baby Yoshi)",
        "de-DE": "Underwater Theme (Baby Yoshi)",
        "nl-NL": "Underwater Theme (Baby Yoshi)",
        "it-IT": "Underwater Theme (Baby Yoshi)",
        "pt-PT": "Underwater Theme (Baby Yoshi)",
        "pt-BR": "Underwater Theme (Baby Yoshi)",
        "es-ES": "Underwater Theme (Baby Yoshi)",
        "es-MX": "Underwater Theme (Baby Yoshi)",
        "ru-RU": "Underwater Theme (Baby Yoshi)",
        "ko-KR": "Underwater Theme (Baby Yoshi)",
        "zh-CN": "Underwater Theme (Baby Yoshi)",
        "zh-TW": "Underwater Theme (Baby Yoshi)"
      }
    },
    {
      "id": "d2f35a8b-98ed-4e6a-841e-c5b58549edf9",
      "name": {
        "en-US": "World: Frosted Glacier",
        "ja-JP": "ワールド：フローズンだいち",
        "en-GB": "World: Frosted Glacier",
        "fr-FR": "World: Frosted Glacier",
        "fr-CA": "World: Frosted Glacier",
        "de-DE": "World: Frosted Glacier",
        "nl-NL": "World: Frosted Glacier",
        "it-IT": "World: Frosted Glacier",
        "pt-PT": "World: Frosted Glacier",
        "pt-BR": "World: Frosted Glacier",
        "es-ES": "World: Frosted Glacier",
        "es-MX": "World: Frosted Glacier",
        "ru-RU": "World: Frosted Glacier",
        "ko-KR": "World: Frosted Glacier",
        "zh-CN": "World: Frosted Glacier",
        "zh-TW": "World: Frosted Glacier"
      }
    },
    {
      "id": "437fea50-0100-4db6-b7c0-713ad5384864",
      "name": {
        "en-US": "Snowfield Theme",
        "ja-JP": "雪原のテーマ",
        "en-GB": "Snowfield Theme",
        "fr-FR": "Snowfield Theme",
        "fr-CA": "Snowfield Theme",
        "de-DE": "Snowfield Theme",
        "nl-NL": "Snowfield Theme",
        "it-IT": "Snowfield Theme",
        "pt-PT": "Snowfield Theme",
        "pt-BR": "Snowfield Theme",
        "es-ES": "Snowfield Theme",
        "es-MX": "Snowfield Theme",
        "ru-RU": "Snowfield Theme",
        "ko-KR": "Snowfield Theme",
        "zh-CN": "Snowfield Theme",
        "zh-TW": "Snowfield Theme"
      }
    },
    {
      "id": "d7fbd635-de46-4bfc-85d2-05c427ff639f",
      "name": {
        "en-US": "Snowfield Theme (Hurry Up!)",
        "ja-JP": "雪原のテーマ（ハリーアップ）",
        "en-GB": "Snowfield Theme (Hurry Up!)",
        "fr-FR": "Snowfield Theme (Hurry Up!)",
        "fr-CA": "Snowfield Theme (Hurry Up!)",
        "de-DE": "Snowfield Theme (Hurry Up!)",
        "nl-NL": "Snowfield Theme (Hurry Up!)",
        "it-IT": "Snowfield Theme (Hurry Up!)",
        "pt-PT": "Snowfield Theme (Hurry Up!)",
        "pt-BR": "Snowfield Theme (Hurry Up!)",
        "es-ES": "Snowfield Theme (Hurry Up!)",
        "es-MX": "Snowfield Theme (Hurry Up!)",
        "ru-RU": "Snowfield Theme (Hurry Up!)",
        "ko-KR": "Snowfield Theme (Hurry Up!)",
        "zh-CN": "Snowfield Theme (Hurry Up!)",
        "zh-TW": "Snowfield Theme (Hurry Up!)"
      }
    },
    {
      "id": "76db8145-ae9c-4e43-94b6-8c9f5a9c7cfe",
      "name": {
        "en-US": "Snowfield Theme (Baby Yoshi)",
        "ja-JP": "雪原のテーマ（ちびヨッシー）",
        "en-GB": "Snowfield Theme (Baby Yoshi)",
        "fr-FR": "Snowfield Theme (Baby Yoshi)",
        "fr-CA": "Snowfield Theme (Baby Yoshi)",
        "de-DE": "Snowfield Theme (Baby Yoshi)",
        "nl-NL": "Snowfield Theme (Baby Yoshi)",
        "it-IT": "Snowfield Theme (Baby Yoshi)",
        "pt-PT": "Snowfield Theme (Baby Yoshi)",
        "pt-BR": "Snowfield Theme (Baby Yoshi)",
        "es-ES": "Snowfield Theme (Baby Yoshi)",
        "es-MX": "Snowfield Theme (Baby Yoshi)",
        "ru-RU": "Snowfield Theme (Baby Yoshi)",
        "ko-KR": "Snowfield Theme (Baby Yoshi)",
        "zh-CN": "Snowfield Theme (Baby Yoshi)",
        "zh-TW": "Snowfield Theme (Baby Yoshi)"
      }
    },
    {
      "id": "c2716d20-a3d4-41f8-82c8-663ce3428173",
      "name": {
        "en-US": "Castle Theme",
        "ja-JP": "城のテーマ",
        "en-GB": "Castle Theme",
        "fr-FR": "Castle Theme",
        "fr-CA": "Castle Theme",
        "de-DE": "Castle Theme",
        "nl-NL": "Castle Theme",
        "it-IT": "Castle Theme",
        "pt-PT": "Castle Theme",
        "pt-BR": "Castle Theme",
        "es-ES": "Castle Theme",
        "es-MX": "Castle Theme",
        "ru-RU": "Castle Theme",
        "ko-KR": "Castle Theme",
        "zh-CN": "Castle Theme",
        "zh-TW": "Castle Theme"
      }
    },
    {
      "id": "6e8ada5a-9ee3-49e8-ac26-9839292c0c40",
      "name": {
        "en-US": "Castle Theme (Hurry Up!)",
        "ja-JP": "城のテーマ（ハリーアップ）",
        "en-GB": "Castle Theme (Hurry Up!)",
        "fr-FR": "Castle Theme (Hurry Up!)",
        "fr-CA": "Castle Theme (Hurry Up!)",
        "de-DE": "Castle Theme (Hurry Up!)",
        "nl-NL": "Castle Theme (Hurry Up!)",
        "it-IT": "Castle Theme (Hurry Up!)",
        "pt-PT": "Castle Theme (Hurry Up!)",
        "pt-BR": "Castle Theme (Hurry Up!)",
        "es-ES": "Castle Theme (Hurry Up!)",
        "es-MX": "Castle Theme (Hurry Up!)",
        "ru-RU": "Castle Theme (Hurry Up!)",
        "ko-KR": "Castle Theme (Hurry Up!)",
        "zh-CN": "Castle Theme (Hurry Up!)",
        "zh-TW": "Castle Theme (Hurry Up!)"
      }
    },
    {
      "id": "3e471aab-7015-411f-a208-e0a601586908",
      "name": {
        "en-US": "Castle Passage",
        "ja-JP": "城の廊下",
        "en-GB": "Castle Passage",
        "fr-FR": "Castle Passage",
        "fr-CA": "Castle Passage",
        "de-DE": "Castle Passage",
        "nl-NL": "Castle Passage",
        "it-IT": "Castle Passage",
        "pt-PT": "Castle Passage",
        "pt-BR": "Castle Passage",
        "es-ES": "Castle Passage",
        "es-MX": "Castle Passage",
        "ru-RU": "Castle Passage",
        "ko-KR": "Castle Passage",
        "zh-CN": "Castle Passage",
        "zh-TW": "Castle Passage"
      }
    },
    {
      "id": "691e3d0d-e49c-4206-b048-2c581a47e3b1",
      "name": {
        "en-US": "Castle Passage (Hurry Up!)",
        "ja-JP": "城の廊下（ハリーアップ）",
        "en-GB": "Castle Passage (Hurry Up!)",
        "fr-FR": "Castle Passage (Hurry Up!)",
        "fr-CA": "Castle Passage (Hurry Up!)",
        "de-DE": "Castle Passage (Hurry Up!)",
        "nl-NL": "Castle Passage (Hurry Up!)",
        "it-IT": "Castle Passage (Hurry Up!)",
        "pt-PT": "Castle Passage (Hurry Up!)",
        "pt-BR": "Castle Passage (Hurry Up!)",
        "es-ES": "Castle Passage (Hurry Up!)",
        "es-MX": "Castle Passage (Hurry Up!)",
        "ru-RU": "Castle Passage (Hurry Up!)",
        "ko-KR": "Castle Passage (Hurry Up!)",
        "zh-CN": "Castle Passage (Hurry Up!)",
        "zh-TW": "Castle Passage (Hurry Up!)"
      }
    },
    {
      "id": "d507935e-513b-41bc-b7a0-2df3cda02a4d",
      "name": {
        "en-US": "Koopaling Battle",
        "ja-JP": "クッパ7人衆戦",
        "en-GB": "Koopaling Battle",
        "fr-FR": "Koopaling Battle",
        "fr-CA": "Koopaling Battle",
        "de-DE": "Koopaling Battle",
        "nl-NL": "Koopaling Battle",
        "it-IT": "Koopaling Battle",
        "pt-PT": "Koopaling Battle",
        "pt-BR": "Koopaling Battle",
        "es-ES": "Koopaling Battle",
        "es-MX": "Koopaling Battle",
        "ru-RU": "Koopaling Battle",
        "ko-KR": "Koopaling Battle",
        "zh-CN": "Koopaling Battle",
        "zh-TW": "Koopaling Battle"
      }
    },
    {
      "id": "0214a6d9-5933-40d3-89e7-4edd42675675",
      "name": {
        "en-US": "Koopaling Battle (Hurry Up!)",
        "ja-JP": "クッパ7人衆戦（ハリーアップ）",
        "en-GB": "Koopaling Battle (Hurry Up!)",
        "fr-FR": "Koopaling Battle (Hurry Up!)",
        "fr-CA": "Koopaling Battle (Hurry Up!)",
        "de-DE": "Koopaling Battle (Hurry Up!)",
        "nl-NL": "Koopaling Battle (Hurry Up!)",
        "it-IT": "Koopaling Battle (Hurry Up!)",
        "pt-PT": "Koopaling Battle (Hurry Up!)",
        "pt-BR": "Koopaling Battle (Hurry Up!)",
        "es-ES": "Koopaling Battle (Hurry Up!)",
        "es-MX": "Koopaling Battle (Hurry Up!)",
        "ru-RU": "Koopaling Battle (Hurry Up!)",
        "ko-KR": "Koopaling Battle (Hurry Up!)",
        "zh-CN": "Koopaling Battle (Hurry Up!)",
        "zh-TW": "Koopaling Battle (Hurry Up!)"
      }
    },
    {
      "id": "37d69e61-c206-416b-8c43-b97582a0f790",
      "name": {
        "en-US": "Too Bad!",
        "ja-JP": "ミス",
        "en-GB": "Too Bad!",
        "fr-FR": "Too Bad!",
        "fr-CA": "Too Bad!",
        "de-DE": "Too Bad!",
        "nl-NL": "Too Bad!",
        "it-IT": "Too Bad!",
        "pt-PT": "Too Bad!",
        "pt-BR": "Too Bad!",
        "es-ES": "Too Bad!",
        "es-MX": "Too Bad!",
        "ru-RU": "Too Bad!",
        "ko-KR": "Too Bad!",
        "zh-CN": "Too Bad!",
        "zh-TW": "Too Bad!"
      }
    },
    {
      "id": "31d043a5-94f3-444d-906d-13520fcbfb31",
      "name": {
        "en-US": "Game Over",
        "ja-JP": "ゲームオーバー",
        "en-GB": "Game Over",
        "fr-FR": "Game Over",
        "fr-CA": "Game Over",
        "de-DE": "Game Over",
        "nl-NL": "Game Over",
        "it-IT": "Game Over",
        "pt-PT": "Game Over",
        "pt-BR": "Game Over",
        "es-ES": "Game Over",
        "es-MX": "Game Over",
        "ru-RU": "Game Over",
        "ko-KR": "Game Over",
        "zh-CN": "Game Over",
        "zh-TW": "Game Over"
      }
    },
    {
      "id": "99eb627a-f0a1-4e9a-ac8c-51a8d1b8a4cd",
      "name": {
        "en-US": "World: Soda Jungle",
        "ja-JP": "ワールド：ソーダジャングル",
        "en-GB": "World: Soda Jungle",
        "fr-FR": "World: Soda Jungle",
        "fr-CA": "World: Soda Jungle",
        "de-DE": "World: Soda Jungle",
        "nl-NL": "World: Soda Jungle",
        "it-IT": "World: Soda Jungle",
        "pt-PT": "World: Soda Jungle",
        "pt-BR": "World: Soda Jungle",
        "es-ES": "World: Soda Jungle",
        "es-MX": "World: Soda Jungle",
        "ru-RU": "World: Soda Jungle",
        "ko-KR": "World: Soda Jungle",
        "zh-CN": "World: Soda Jungle",
        "zh-TW": "World: Soda Jungle"
      }
    },
    {
      "id": "e753a978-eb7b-43ea-b6b9-bda363e24f5b",
      "name": {
        "en-US": "Forest Theme",
        "ja-JP": "森のテーマ",
        "en-GB": "Forest Theme",
        "fr-FR": "Forest Theme",
        "fr-CA": "Forest Theme",
        "de-DE": "Forest Theme",
        "nl-NL": "Forest Theme",
        "it-IT": "Forest Theme",
        "pt-PT": "Forest Theme",
        "pt-BR": "Forest Theme",
        "es-ES": "Forest Theme",
        "es-MX": "Forest Theme",
        "ru-RU": "Forest Theme",
        "ko-KR": "Forest Theme",
        "zh-CN": "Forest Theme",
        "zh-TW": "Forest Theme"
      }
    },
    {
      "id": "09c4b1ed-454c-41d5-933d-b7c46b658015",
      "name": {
        "en-US": "Forest Theme (Hurry Up!)",
        "ja-JP": "森のテーマ（ハリーアップ）",
        "en-GB": "Forest Theme (Hurry Up!)",
        "fr-FR": "Forest Theme (Hurry Up!)",
        "fr-CA": "Forest Theme (Hurry Up!)",
        "de-DE": "Forest Theme (Hurry Up!)",
        "nl-NL": "Forest Theme (Hurry Up!)",
        "it-IT": "Forest Theme (Hurry Up!)",
        "pt-PT": "Forest Theme (Hurry Up!)",
        "pt-BR": "Forest Theme (Hurry Up!)",
        "es-ES": "Forest Theme (Hurry Up!)",
        "es-MX": "Forest Theme (Hurry Up!)",
        "ru-RU": "Forest Theme (Hurry Up!)",
        "ko-KR": "Forest Theme (Hurry Up!)",
        "zh-CN": "Forest Theme (Hurry Up!)",
        "zh-TW": "Forest Theme (Hurry Up!)"
      }
    },
    {
      "id": "6555c429-4b3b-4c28-b848-e00cca896685",
      "name": {
        "en-US": "Forest Theme (Baby Yoshi)",
        "ja-JP": "森のテーマ（ちびヨッシー）",
        "en-GB": "Forest Theme (Baby Yoshi)",
        "fr-FR": "Forest Theme (Baby Yoshi)",
        "fr-CA": "Forest Theme (Baby Yoshi)",
        "de-DE": "Forest Theme (Baby Yoshi)",
        "nl-NL": "Forest Theme (Baby Yoshi)",
        "it-IT": "Forest Theme (Baby Yoshi)",
        "pt-PT": "Forest Theme (Baby Yoshi)",
        "pt-BR": "Forest Theme (Baby Yoshi)",
        "es-ES": "Forest Theme (Baby Yoshi)",
        "es-MX": "Forest Theme (Baby Yoshi)",
        "ru-RU": "Forest Theme (Baby Yoshi)",
        "ko-KR": "Forest Theme (Baby Yoshi)",
        "zh-CN": "Forest Theme (Baby Yoshi)",
        "zh-TW": "Forest Theme (Baby Yoshi)"
      }
    },
    {
      "id": "e50ba845-77fe-408d-aed7-804a5ef4c1fd",
      "name": {
        "en-US": "World: Soda Jungle (Ghost House Area)",
        "ja-JP": "ワールド：ソーダジャングル おばけやしきエリア",
        "en-GB": "World: Soda Jungle (Ghost House Area)",
        "fr-FR": "World: Soda Jungle (Ghost House Area)",
        "fr-CA": "World: Soda Jungle (Ghost House Area)",
        "de-DE": "World: Soda Jungle (Ghost House Area)",
        "nl-NL": "World: Soda Jungle (Ghost House Area)",
        "it-IT": "World: Soda Jungle (Ghost House Area)",
        "pt-PT": "World: Soda Jungle (Ghost House Area)",
        "pt-BR": "World: Soda Jungle (Ghost House Area)",
        "es-ES": "World: Soda Jungle (Ghost House Area)",
        "es-MX": "World: Soda Jungle (Ghost House Area)",
        "ru-RU": "World: Soda Jungle (Ghost House Area)",
        "ko-KR": "World: Soda Jungle (Ghost House Area)",
        "zh-CN": "World: Soda Jungle (Ghost House Area)",
        "zh-TW": "World: Soda Jungle (Ghost House Area)"
      }
    },
    {
      "id": "87aee81e-1196-4fdb-882d-090d2202c73b",
      "name": {
        "en-US": "Ghost House Theme",
        "ja-JP": "おばけやしきのテーマ",
        "en-GB": "Ghost House Theme",
        "fr-FR": "Ghost House Theme",
        "fr-CA": "Ghost House Theme",
        "de-DE": "Ghost House Theme",
        "nl-NL": "Ghost House Theme",
        "it-IT": "Ghost House Theme",
        "pt-PT": "Ghost House Theme",
        "pt-BR": "Ghost House Theme",
        "es-ES": "Ghost House Theme",
        "es-MX": "Ghost House Theme",
        "ru-RU": "Ghost House Theme",
        "ko-KR": "Ghost House Theme",
        "zh-CN": "Ghost House Theme",
        "zh-TW": "Ghost House Theme"
      }
    },
    {
      "id": "c7db6732-dd73-4283-a65d-192282f35cd1",
      "name": {
        "en-US": "Ghost House Theme (Hurry Up!)",
        "ja-JP": "おばけやしきのテーマ（ハリーアップ）",
        "en-GB": "Ghost House Theme (Hurry Up!)",
        "fr-FR": "Ghost House Theme (Hurry Up!)",
        "fr-CA": "Ghost House Theme (Hurry Up!)",
        "de-DE": "Ghost House Theme (Hurry Up!)",
        "nl-NL": "Ghost House Theme (Hurry Up!)",
        "it-IT": "Ghost House Theme (Hurry Up!)",
        "pt-PT": "Ghost House Theme (Hurry Up!)",
        "pt-BR": "Ghost House Theme (Hurry Up!)",
        "es-ES": "Ghost House Theme (Hurry Up!)",
        "es-MX": "Ghost House Theme (Hurry Up!)",
        "ru-RU": "Ghost House Theme (Hurry Up!)",
        "ko-KR": "Ghost House Theme (Hurry Up!)",
        "zh-CN": "Ghost House Theme (Hurry Up!)",
        "zh-TW": "Ghost House Theme (Hurry Up!)"
      }
    },
    {
      "id": "472c7584-c232-40b0-a949-f8c815943201",
      "name": {
        "en-US": "Ghost House Theme (Baby Yoshi)",
        "ja-JP": "おばけやしきのテーマ（ちびヨッシー）",
        "en-GB": "Ghost House Theme (Baby Yoshi)",
        "fr-FR": "Ghost House Theme (Baby Yoshi)",
        "fr-CA": "Ghost House Theme (Baby Yoshi)",
        "de-DE": "Ghost House Theme (Baby Yoshi)",
        "nl-NL": "Ghost House Theme (Baby Yoshi)",
        "it-IT": "Ghost House Theme (Baby Yoshi)",
        "pt-PT": "Ghost House Theme (Baby Yoshi)",
        "pt-BR": "Ghost House Theme (Baby Yoshi)",
        "es-ES": "Ghost House Theme (Baby Yoshi)",
        "es-MX": "Ghost House Theme (Baby Yoshi)",
        "ru-RU": "Ghost House Theme (Baby Yoshi)",
        "ko-KR": "Ghost House Theme (Baby Yoshi)",
        "zh-CN": "Ghost House Theme (Baby Yoshi)",
        "zh-TW": "Ghost House Theme (Baby Yoshi)"
      }
    },
    {
      "id": "06ecb415-bfee-4b81-9f54-6c996e4d42ec",
      "name": {
        "en-US": "World: Rock-Candy Mines",
        "ja-JP": "ワールド：ロックさんみゃく",
        "en-GB": "World: Rock-Candy Mines",
        "fr-FR": "World: Rock-Candy Mines",
        "fr-CA": "World: Rock-Candy Mines",
        "de-DE": "World: Rock-Candy Mines",
        "nl-NL": "World: Rock-Candy Mines",
        "it-IT": "World: Rock-Candy Mines",
        "pt-PT": "World: Rock-Candy Mines",
        "pt-BR": "World: Rock-Candy Mines",
        "es-ES": "World: Rock-Candy Mines",
        "es-MX": "World: Rock-Candy Mines",
        "ru-RU": "World: Rock-Candy Mines",
        "ko-KR": "World: Rock-Candy Mines",
        "zh-CN": "World: Rock-Candy Mines",
        "zh-TW": "World: Rock-Candy Mines"
      }
    },
    {
      "id": "61742888-9b35-4e00-ab00-27fd761e7bc6",
      "name": {
        "en-US": "Athletic Theme",
        "ja-JP": "アスレチックのテーマ",
        "en-GB": "Athletic Theme",
        "fr-FR": "Athletic Theme",
        "fr-CA": "Athletic Theme",
        "de-DE": "Athletic Theme",
        "nl-NL": "Athletic Theme",
        "it-IT": "Athletic Theme",
        "pt-PT": "Athletic Theme",
        "pt-BR": "Athletic Theme",
        "es-ES": "Athletic Theme",
        "es-MX": "Athletic Theme",
        "ru-RU": "Athletic Theme",
        "ko-KR": "Athletic Theme",
        "zh-CN": "Athletic Theme",
        "zh-TW": "Athletic Theme"
      }
    },
    {
      "id": "ede0a01a-3763-489d-8aa0-60cc9e3664cd",
      "name": {
        "en-US": "Athletic Theme (Hurry Up!)",
        "ja-JP": "アスレチックのテーマ（ハリーアップ）",
        "en-GB": "Athletic Theme (Hurry Up!)",
        "fr-FR": "Athletic Theme (Hurry Up!)",
        "fr-CA": "Athletic Theme (Hurry Up!)",
        "de-DE": "Athletic Theme (Hurry Up!)",
        "nl-NL": "Athletic Theme (Hurry Up!)",
        "it-IT": "Athletic Theme (Hurry Up!)",
        "pt-PT": "Athletic Theme (Hurry Up!)",
        "pt-BR": "Athletic Theme (Hurry Up!)",
        "es-ES": "Athletic Theme (Hurry Up!)",
        "es-MX": "Athletic Theme (Hurry Up!)",
        "ru-RU": "Athletic Theme (Hurry Up!)",
        "ko-KR": "Athletic Theme (Hurry Up!)",
        "zh-CN": "Athletic Theme (Hurry Up!)",
        "zh-TW": "Athletic Theme (Hurry Up!)"
      }
    },
    {
      "id": "f5d95b5a-a79c-4f12-a429-acb772733a9b",
      "name": {
        "en-US": "Athletic Theme (Baby Yoshi)",
        "ja-JP": "アスレチックのテーマ（ちびヨッシー）",
        "en-GB": "Athletic Theme (Baby Yoshi)",
        "fr-FR": "Athletic Theme (Baby Yoshi)",
        "fr-CA": "Athletic Theme (Baby Yoshi)",
        "de-DE": "Athletic Theme (Baby Yoshi)",
        "nl-NL": "Athletic Theme (Baby Yoshi)",
        "it-IT": "Athletic Theme (Baby Yoshi)",
        "pt-PT": "Athletic Theme (Baby Yoshi)",
        "pt-BR": "Athletic Theme (Baby Yoshi)",
        "es-ES": "Athletic Theme (Baby Yoshi)",
        "es-MX": "Athletic Theme (Baby Yoshi)",
        "ru-RU": "Athletic Theme (Baby Yoshi)",
        "ko-KR": "Athletic Theme (Baby Yoshi)",
        "zh-CN": "Athletic Theme (Baby Yoshi)",
        "zh-TW": "Athletic Theme (Baby Yoshi)"
      }
    },
    {
      "id": "81ab9100-6e99-4a48-8065-2d374274a606",
      "name": {
        "en-US": "Bonus Area",
        "ja-JP": "ボーナスエリア",
        "en-GB": "Bonus Area",
        "fr-FR": "Bonus Area",
        "fr-CA": "Bonus Area",
        "de-DE": "Bonus Area",
        "nl-NL": "Bonus Area",
        "it-IT": "Bonus Area",
        "pt-PT": "Bonus Area",
        "pt-BR": "Bonus Area",
        "es-ES": "Bonus Area",
        "es-MX": "Bonus Area",
        "ru-RU": "Bonus Area",
        "ko-KR": "Bonus Area",
        "zh-CN": "Bonus Area",
        "zh-TW": "Bonus Area"
      }
    },
    {
      "id": "9ffa255d-f4dd-4030-afcd-9b5fc24a0a4d",
      "name": {
        "en-US": "Bonus Area (Hurry Up!)",
        "ja-JP": "ボーナスエリア（ハリーアップ）",
        "en-GB": "Bonus Area (Hurry Up!)",
        "fr-FR": "Bonus Area (Hurry Up!)",
        "fr-CA": "Bonus Area (Hurry Up!)",
        "de-DE": "Bonus Area (Hurry Up!)",
        "nl-NL": "Bonus Area (Hurry Up!)",
        "it-IT": "Bonus Area (Hurry Up!)",
        "pt-PT": "Bonus Area (Hurry Up!)",
        "pt-BR": "Bonus Area (Hurry Up!)",
        "es-ES": "Bonus Area (Hurry Up!)",
        "es-MX": "Bonus Area (Hurry Up!)",
        "ru-RU": "Bonus Area (Hurry Up!)",
        "ko-KR": "Bonus Area (Hurry Up!)",
        "zh-CN": "Bonus Area (Hurry Up!)",
        "zh-TW": "Bonus Area (Hurry Up!)"
      }
    },
    {
      "id": "2465bd90-60c9-4c53-a25f-a753b862d2e7",
      "name": {
        "en-US": "Bonus Area (Baby Yoshi)",
        "ja-JP": "ボーナスエリア（ちびヨッシー）",
        "en-GB": "Bonus Area (Baby Yoshi)",
        "fr-FR": "Bonus Area (Baby Yoshi)",
        "fr-CA": "Bonus Area (Baby Yoshi)",
        "de-DE": "Bonus Area (Baby Yoshi)",
        "nl-NL": "Bonus Area (Baby Yoshi)",
        "it-IT": "Bonus Area (Baby Yoshi)",
        "pt-PT": "Bonus Area (Baby Yoshi)",
        "pt-BR": "Bonus Area (Baby Yoshi)",
        "es-ES": "Bonus Area (Baby Yoshi)",
        "es-MX": "Bonus Area (Baby Yoshi)",
        "ru-RU": "Bonus Area (Baby Yoshi)",
        "ko-KR": "Bonus Area (Baby Yoshi)",
        "zh-CN": "Bonus Area (Baby Yoshi)",
        "zh-TW": "Bonus Area (Baby Yoshi)"
      }
    },
    {
      "id": "50747825-89a9-4360-8f97-638dab7c0e7d",
      "name": {
        "en-US": "World: Meringue Clouds",
        "ja-JP": "ワールド：マシュマロうんかい",
        "en-GB": "World: Meringue Clouds",
        "fr-FR": "World: Meringue Clouds",
        "fr-CA": "World: Meringue Clouds",
        "de-DE": "World: Meringue Clouds",
        "nl-NL": "World: Meringue Clouds",
        "it-IT": "World: Meringue Clouds",
        "pt-PT": "World: Meringue Clouds",
        "pt-BR": "World: Meringue Clouds",
        "es-ES": "World: Meringue Clouds",
        "es-MX": "World: Meringue Clouds",
        "ru-RU": "World: Meringue Clouds",
        "ko-KR": "World: Meringue Clouds",
        "zh-CN": "World: Meringue Clouds",
        "zh-TW": "World: Meringue Clouds"
      }
    },
    {
      "id": "a20016f4-aef3-4053-8330-9c37db7ed6f8",
      "name": {
        "en-US": "Switch On!",
        "ja-JP": "スイッチ",
        "en-GB": "Switch On!",
        "fr-FR": "Switch On!",
        "fr-CA": "Switch On!",
        "de-DE": "Switch On!",
        "nl-NL": "Switch On!",
        "it-IT": "Switch On!",
        "pt-PT": "Switch On!",
        "pt-BR": "Switch On!",
        "es-ES": "Switch On!",
        "es-MX": "Switch On!",
        "ru-RU": "Switch On!",
        "ko-KR": "Switch On!",
        "zh-CN": "Switch On!",
        "zh-TW": "Switch On!"
      }
    },
    {
      "id": "9ae11d59-5a66-4a41-b418-69e5c96467f1",
      "name": {
        "en-US": "Super Star",
        "ja-JP": "スター無敵",
        "en-GB": "Super Star",
        "fr-FR": "Super Star",
        "fr-CA": "Super Star",
        "de-DE": "Super Star",
        "nl-NL": "Super Star",
        "it-IT": "Super Star",
        "pt-PT": "Super Star",
        "pt-BR": "Super Star",
        "es-ES": "Super Star",
        "es-MX": "Super Star",
        "ru-RU": "Super Star",
        "ko-KR": "Super Star",
        "zh-CN": "Super Star",
        "zh-TW": "Super Star"
      }
    },
    {
      "id": "77c37966-495c-43eb-af6c-154211b82961",
      "name": {
        "en-US": "Super Star (Hurry Up!)",
        "ja-JP": "スター無敵（ハリーアップ）",
        "en-GB": "Super Star (Hurry Up!)",
        "fr-FR": "Super Star (Hurry Up!)",
        "fr-CA": "Super Star (Hurry Up!)",
        "de-DE": "Super Star (Hurry Up!)",
        "nl-NL": "Super Star (Hurry Up!)",
        "it-IT": "Super Star (Hurry Up!)",
        "pt-PT": "Super Star (Hurry Up!)",
        "pt-BR": "Super Star (Hurry Up!)",
        "es-ES": "Super Star (Hurry Up!)",
        "es-MX": "Super Star (Hurry Up!)",
        "ru-RU": "Super Star (Hurry Up!)",
        "ko-KR": "Super Star (Hurry Up!)",
        "zh-CN": "Super Star (Hurry Up!)",
        "zh-TW": "Super Star (Hurry Up!)"
      }
    },
    {
      "id": "15f1505c-9189-4893-8c2d-3f74880992f2",
      "name": {
        "en-US": "Super Star (Baby Yoshi)",
        "ja-JP": "スター無敵（ちびヨッシー）",
        "en-GB": "Super Star (Baby Yoshi)",
        "fr-FR": "Super Star (Baby Yoshi)",
        "fr-CA": "Super Star (Baby Yoshi)",
        "de-DE": "Super Star (Baby Yoshi)",
        "nl-NL": "Super Star (Baby Yoshi)",
        "it-IT": "Super Star (Baby Yoshi)",
        "pt-PT": "Super Star (Baby Yoshi)",
        "pt-BR": "Super Star (Baby Yoshi)",
        "es-ES": "Super Star (Baby Yoshi)",
        "es-MX": "Super Star (Baby Yoshi)",
        "ru-RU": "Super Star (Baby Yoshi)",
        "ko-KR": "Super Star (Baby Yoshi)",
        "zh-CN": "Super Star (Baby Yoshi)",
        "zh-TW": "Super Star (Baby Yoshi)"
      }
    },
    {
      "id": "d815a458-aa84-47bf-b975-1426fa055239",
      "name": {
        "en-US": "Airship Theme",
        "ja-JP": "飛行船のテーマ",
        "en-GB": "Airship Theme",
        "fr-FR": "Airship Theme",
        "fr-CA": "Airship Theme",
        "de-DE": "Airship Theme",
        "nl-NL": "Airship Theme",
        "it-IT": "Airship Theme",
        "pt-PT": "Airship Theme",
        "pt-BR": "Airship Theme",
        "es-ES": "Airship Theme",
        "es-MX": "Airship Theme",
        "ru-RU": "Airship Theme",
        "ko-KR": "Airship Theme",
        "zh-CN": "Airship Theme",
        "zh-TW": "Airship Theme"
      }
    },
    {
      "id": "aa2c803f-8da5-4a35-839b-b1a21e4dc24d",
      "name": {
        "en-US": "Airship Theme (Hurry Up!)",
        "ja-JP": "飛行船のテーマ（ハリーアップ）",
        "en-GB": "Airship Theme (Hurry Up!)",
        "fr-FR": "Airship Theme (Hurry Up!)",
        "fr-CA": "Airship Theme (Hurry Up!)",
        "de-DE": "Airship Theme (Hurry Up!)",
        "nl-NL": "Airship Theme (Hurry Up!)",
        "it-IT": "Airship Theme (Hurry Up!)",
        "pt-PT": "Airship Theme (Hurry Up!)",
        "pt-BR": "Airship Theme (Hurry Up!)",
        "es-ES": "Airship Theme (Hurry Up!)",
        "es-MX": "Airship Theme (Hurry Up!)",
        "ru-RU": "Airship Theme (Hurry Up!)",
        "ko-KR": "Airship Theme (Hurry Up!)",
        "zh-CN": "Airship Theme (Hurry Up!)",
        "zh-TW": "Airship Theme (Hurry Up!)"
      }
    },
    {
      "id": "730a88fb-35b0-498b-a8d4-5e4e160facda",
      "name": {
        "en-US": "Bowser Jr. Battle",
        "ja-JP": "クッパJr.戦",
        "en-GB": "Bowser Jr. Battle",
        "fr-FR": "Bowser Jr. Battle",
        "fr-CA": "Bowser Jr. Battle",
        "de-DE": "Bowser Jr. Battle",
        "nl-NL": "Bowser Jr. Battle",
        "it-IT": "Bowser Jr. Battle",
        "pt-PT": "Bowser Jr. Battle",
        "pt-BR": "Bowser Jr. Battle",
        "es-ES": "Bowser Jr. Battle",
        "es-MX": "Bowser Jr. Battle",
        "ru-RU": "Bowser Jr. Battle",
        "ko-KR": "Bowser Jr. Battle",
        "zh-CN": "Bowser Jr. Battle",
        "zh-TW": "Bowser Jr. Battle"
      }
    },
    {
      "id": "04d0fcba-65e5-4dbb-b142-b39eb3c66f23",
      "name": {
        "en-US": "Bowser Jr. Battle (Hurry Up!)",
        "ja-JP": "クッパJr.戦（ハリーアップ）",
        "en-GB": "Bowser Jr. Battle (Hurry Up!)",
        "fr-FR": "Bowser Jr. Battle (Hurry Up!)",
        "fr-CA": "Bowser Jr. Battle (Hurry Up!)",
        "de-DE": "Bowser Jr. Battle (Hurry Up!)",
        "nl-NL": "Bowser Jr. Battle (Hurry Up!)",
        "it-IT": "Bowser Jr. Battle (Hurry Up!)",
        "pt-PT": "Bowser Jr. Battle (Hurry Up!)",
        "pt-BR": "Bowser Jr. Battle (Hurry Up!)",
        "es-ES": "Bowser Jr. Battle (Hurry Up!)",
        "es-MX": "Bowser Jr. Battle (Hurry Up!)",
        "ru-RU": "Bowser Jr. Battle (Hurry Up!)",
        "ko-KR": "Bowser Jr. Battle (Hurry Up!)",
        "zh-CN": "Bowser Jr. Battle (Hurry Up!)",
        "zh-TW": "Bowser Jr. Battle (Hurry Up!)"
      }
    },
    {
      "id": "dc09fa95-a838-43a5-9337-434df98c56b1",
      "name": {
        "en-US": "World: Peach's Castle",
        "ja-JP": "ワールド：ピーチ城",
        "en-GB": "World: Peach's Castle",
        "fr-FR": "World: Peach's Castle",
        "fr-CA": "World: Peach's Castle",
        "de-DE": "World: Peach's Castle",
        "nl-NL": "World: Peach's Castle",
        "it-IT": "World: Peach's Castle",
        "pt-PT": "World: Peach's Castle",
        "pt-BR": "World: Peach's Castle",
        "es-ES": "World: Peach's Castle",
        "es-MX": "World: Peach's Castle",
        "ru-RU": "World: Peach's Castle",
        "ko-KR": "World: Peach's Castle",
        "zh-CN": "World: Peach's Castle",
        "zh-TW": "World: Peach's Castle"
      }
    },
    {
      "id": "d81d3c55-326e-40af-9e14-11c13d05aba9",
      "name": {
        "en-US": "Lava Theme",
        "ja-JP": "溶岩のテーマ",
        "en-GB": "Lava Theme",
        "fr-FR": "Lava Theme",
        "fr-CA": "Lava Theme",
        "de-DE": "Lava Theme",
        "nl-NL": "Lava Theme",
        "it-IT": "Lava Theme",
        "pt-PT": "Lava Theme",
        "pt-BR": "Lava Theme",
        "es-ES": "Lava Theme",
        "es-MX": "Lava Theme",
        "ru-RU": "Lava Theme",
        "ko-KR": "Lava Theme",
        "zh-CN": "Lava Theme",
        "zh-TW": "Lava Theme"
      }
    },
    {
      "id": "e737dcff-0f82-4e6b-b371-5caf8e2ed9c2",
      "name": {
        "en-US": "Lava Theme (Hurry Up!)",
        "ja-JP": "溶岩のテーマ（ハリーアップ）",
        "en-GB": "Lava Theme (Hurry Up!)",
        "fr-FR": "Lava Theme (Hurry Up!)",
        "fr-CA": "Lava Theme (Hurry Up!)",
        "de-DE": "Lava Theme (Hurry Up!)",
        "nl-NL": "Lava Theme (Hurry Up!)",
        "it-IT": "Lava Theme (Hurry Up!)",
        "pt-PT": "Lava Theme (Hurry Up!)",
        "pt-BR": "Lava Theme (Hurry Up!)",
        "es-ES": "Lava Theme (Hurry Up!)",
        "es-MX": "Lava Theme (Hurry Up!)",
        "ru-RU": "Lava Theme (Hurry Up!)",
        "ko-KR": "Lava Theme (Hurry Up!)",
        "zh-CN": "Lava Theme (Hurry Up!)",
        "zh-TW": "Lava Theme (Hurry Up!)"
      }
    },
    {
      "id": "b72cab24-61ac-4b74-bf11-7bf4f6d58515",
      "name": {
        "en-US": "Lava Theme (Baby Yoshi)",
        "ja-JP": "溶岩のテーマ（ちびヨッシー）",
        "en-GB": "Lava Theme (Baby Yoshi)",
        "fr-FR": "Lava Theme (Baby Yoshi)",
        "fr-CA": "Lava Theme (Baby Yoshi)",
        "de-DE": "Lava Theme (Baby Yoshi)",
        "nl-NL": "Lava Theme (Baby Yoshi)",
        "it-IT": "Lava Theme (Baby Yoshi)",
        "pt-PT": "Lava Theme (Baby Yoshi)",
        "pt-BR": "Lava Theme (Baby Yoshi)",
        "es-ES": "Lava Theme (Baby Yoshi)",
        "es-MX": "Lava Theme (Baby Yoshi)",
        "ru-RU": "Lava Theme (Baby Yoshi)",
        "ko-KR": "Lava Theme (Baby Yoshi)",
        "zh-CN": "Lava Theme (Baby Yoshi)",
        "zh-TW": "Lava Theme (Baby Yoshi)"
      }
    },
    {
      "id": "11d387e9-65d0-4653-b037-957c51e11447",
      "name": {
        "en-US": "Lava Cave / Underground Ruins Theme",
        "ja-JP": "溶岩洞窟・地下遺跡のテーマ",
        "en-GB": "Lava Cave / Underground Ruins Theme",
        "fr-FR": "Lava Cave / Underground Ruins Theme",
        "fr-CA": "Lava Cave / Underground Ruins Theme",
        "de-DE": "Lava Cave / Underground Ruins Theme",
        "nl-NL": "Lava Cave / Underground Ruins Theme",
        "it-IT": "Lava Cave / Underground Ruins Theme",
        "pt-PT": "Lava Cave / Underground Ruins Theme",
        "pt-BR": "Lava Cave / Underground Ruins Theme",
        "es-ES": "Lava Cave / Underground Ruins Theme",
        "es-MX": "Lava Cave / Underground Ruins Theme",
        "ru-RU": "Lava Cave / Underground Ruins Theme",
        "ko-KR": "Lava Cave / Underground Ruins Theme",
        "zh-CN": "Lava Cave / Underground Ruins Theme",
        "zh-TW": "Lava Cave / Underground Ruins Theme"
      }
    },
    {
      "id": "d8b1d37b-daa5-4ae1-b4dd-e5ddafeee351",
      "name": {
        "en-US": "Lava Cave / Underground Ruins Theme (Hurry Up!)",
        "ja-JP": "溶岩洞窟・地下遺跡のテーマ（ハリーアップ）",
        "en-GB": "Lava Cave / Underground Ruins Theme (Hurry Up!)",
        "fr-FR": "Lava Cave / Underground Ruins Theme (Hurry Up!)",
        "fr-CA": "Lava Cave / Underground Ruins Theme (Hurry Up!)",
        "de-DE": "Lava Cave / Underground Ruins Theme (Hurry Up!)",
        "nl-NL": "Lava Cave / Underground Ruins Theme (Hurry Up!)",
        "it-IT": "Lava Cave / Underground Ruins Theme (Hurry Up!)",
        "pt-PT": "Lava Cave / Underground Ruins Theme (Hurry Up!)",
        "pt-BR": "Lava Cave / Underground Ruins Theme (Hurry Up!)",
        "es-ES": "Lava Cave / Underground Ruins Theme (Hurry Up!)",
        "es-MX": "Lava Cave / Underground Ruins Theme (Hurry Up!)",
        "ru-RU": "Lava Cave / Underground Ruins Theme (Hurry Up!)",
        "ko-KR": "Lava Cave / Underground Ruins Theme (Hurry Up!)",
        "zh-CN": "Lava Cave / Underground Ruins Theme (Hurry Up!)",
        "zh-TW": "Lava Cave / Underground Ruins Theme (Hurry Up!)"
      }
    },
    {
      "id": "6ae7b1ff-e294-4964-b559-3ee6c59baefc",
      "name": {
        "en-US": "Lava Cave / Underground Ruins Theme (Baby Yoshi)",
        "ja-JP": "溶岩洞窟・地下遺跡のテーマ（ちびヨッシー）",
        "en-GB": "Lava Cave / Underground Ruins Theme (Baby Yoshi)",
        "fr-FR": "Lava Cave / Underground Ruins Theme (Baby Yoshi)",
        "fr-CA": "Lava Cave / Underground Ruins Theme (Baby Yoshi)",
        "de-DE": "Lava Cave / Underground Ruins Theme (Baby Yoshi)",
        "nl-NL": "Lava Cave / Underground Ruins Theme (Baby Yoshi)",
        "it-IT": "Lava Cave / Underground Ruins Theme (Baby Yoshi)",
        "pt-PT": "Lava Cave / Underground Ruins Theme (Baby Yoshi)",
        "pt-BR": "Lava Cave / Underground Ruins Theme (Baby Yoshi)",
        "es-ES": "Lava Cave / Underground Ruins Theme (Baby Yoshi)",
        "es-MX": "Lava Cave / Underground Ruins Theme (Baby Yoshi)",
        "ru-RU": "Lava Cave / Underground Ruins Theme (Baby Yoshi)",
        "ko-KR": "Lava Cave / Underground Ruins Theme (Baby Yoshi)",
        "zh-CN": "Lava Cave / Underground Ruins Theme (Baby Yoshi)",
        "zh-TW": "Lava Cave / Underground Ruins Theme (Baby Yoshi)"
      }
    },
    {
      "id": "37772fdb-90e8-4965-9f70-67e31cb2e8ae",
      "name": {
        "en-US": "Big Battle at Peach's Castle",
        "ja-JP": "けっせん！ピーチ城",
        "en-GB": "Big Battle at Peach's Castle",
        "fr-FR": "Big Battle at Peach's Castle",
        "fr-CA": "Big Battle at Peach's Castle",
        "de-DE": "Big Battle at Peach's Castle",
        "nl-NL": "Big Battle at Peach's Castle",
        "it-IT": "Big Battle at Peach's Castle",
        "pt-PT": "Big Battle at Peach's Castle",
        "pt-BR": "Big Battle at Peach's Castle",
        "es-ES": "Big Battle at Peach's Castle",
        "es-MX": "Big Battle at Peach's Castle",
        "ru-RU": "Big Battle at Peach's Castle",
        "ko-KR": "Big Battle at Peach's Castle",
        "zh-CN": "Big Battle at Peach's Castle",
        "zh-TW": "Big Battle at Peach's Castle"
      }
    },
    {
      "id": "9e4bc7e1-4282-4eca-b864-59dfd1222728",
      "name": {
        "en-US": "Big Battle at Peach's Castle (Hurry Up!)",
        "ja-JP": "けっせん！ピーチ城（ハリーアップ）",
        "en-GB": "Big Battle at Peach's Castle (Hurry Up!)",
        "fr-FR": "Big Battle at Peach's Castle (Hurry Up!)",
        "fr-CA": "Big Battle at Peach's Castle (Hurry Up!)",
        "de-DE": "Big Battle at Peach's Castle (Hurry Up!)",
        "nl-NL": "Big Battle at Peach's Castle (Hurry Up!)",
        "it-IT": "Big Battle at Peach's Castle (Hurry Up!)",
        "pt-PT": "Big Battle at Peach's Castle (Hurry Up!)",
        "pt-BR": "Big Battle at Peach's Castle (Hurry Up!)",
        "es-ES": "Big Battle at Peach's Castle (Hurry Up!)",
        "es-MX": "Big Battle at Peach's Castle (Hurry Up!)",
        "ru-RU": "Big Battle at Peach's Castle (Hurry Up!)",
        "ko-KR": "Big Battle at Peach's Castle (Hurry Up!)",
        "zh-CN": "Big Battle at Peach's Castle (Hurry Up!)",
        "zh-TW": "Big Battle at Peach's Castle (Hurry Up!)"
      }
    },
    {
      "id": "721b202f-7466-42ad-b67f-e2000bf992ab",
      "name": {
        "en-US": "Peach's Castle Passage",
        "ja-JP": "ピーチ城の廊下",
        "en-GB": "Peach's Castle Passage",
        "fr-FR": "Peach's Castle Passage",
        "fr-CA": "Peach's Castle Passage",
        "de-DE": "Peach's Castle Passage",
        "nl-NL": "Peach's Castle Passage",
        "it-IT": "Peach's Castle Passage",
        "pt-PT": "Peach's Castle Passage",
        "pt-BR": "Peach's Castle Passage",
        "es-ES": "Peach's Castle Passage",
        "es-MX": "Peach's Castle Passage",
        "ru-RU": "Peach's Castle Passage",
        "ko-KR": "Peach's Castle Passage",
        "zh-CN": "Peach's Castle Passage",
        "zh-TW": "Peach's Castle Passage"
      }
    },
    {
      "id": "ad6ed431-2ccf-42bf-a130-dad817a88cbc",
      "name": {
        "en-US": "Peach's Castle Passage (Hurry Up!)",
        "ja-JP": "ピーチ城の廊下（ハリーアップ）",
        "en-GB": "Peach's Castle Passage (Hurry Up!)",
        "fr-FR": "Peach's Castle Passage (Hurry Up!)",
        "fr-CA": "Peach's Castle Passage (Hurry Up!)",
        "de-DE": "Peach's Castle Passage (Hurry Up!)",
        "nl-NL": "Peach's Castle Passage (Hurry Up!)",
        "it-IT": "Peach's Castle Passage (Hurry Up!)",
        "pt-PT": "Peach's Castle Passage (Hurry Up!)",
        "pt-BR": "Peach's Castle Passage (Hurry Up!)",
        "es-ES": "Peach's Castle Passage (Hurry Up!)",
        "es-MX": "Peach's Castle Passage (Hurry Up!)",
        "ru-RU": "Peach's Castle Passage (Hurry Up!)",
        "ko-KR": "Peach's Castle Passage (Hurry Up!)",
        "zh-CN": "Peach's Castle Passage (Hurry Up!)",
        "zh-TW": "Peach's Castle Passage (Hurry Up!)"
      }
    },
    {
      "id": "57558dac-b7f7-4874-b654-3a098c93f4a8",
      "name": {
        "en-US": "Bowser Battle 1",
        "ja-JP": "クッパ戦 その1",
        "en-GB": "Bowser Battle 1",
        "fr-FR": "Bowser Battle 1",
        "fr-CA": "Bowser Battle 1",
        "de-DE": "Bowser Battle 1",
        "nl-NL": "Bowser Battle 1",
        "it-IT": "Bowser Battle 1",
        "pt-PT": "Bowser Battle 1",
        "pt-BR": "Bowser Battle 1",
        "es-ES": "Bowser Battle 1",
        "es-MX": "Bowser Battle 1",
        "ru-RU": "Bowser Battle 1",
        "ko-KR": "Bowser Battle 1",
        "zh-CN": "Bowser Battle 1",
        "zh-TW": "Bowser Battle 1"
      }
    },
    {
      "id": "98985c17-97e6-4d37-b3b0-63ac1a6a8e98",
      "name": {
        "en-US": "Bowser Battle 1 (Hurry Up!)",
        "ja-JP": "クッパ戦 その1（ハリーアップ）",
        "en-GB": "Bowser Battle 1 (Hurry Up!)",
        "fr-FR": "Bowser Battle 1 (Hurry Up!)",
        "fr-CA": "Bowser Battle 1 (Hurry Up!)",
        "de-DE": "Bowser Battle 1 (Hurry Up!)",
        "nl-NL": "Bowser Battle 1 (Hurry Up!)",
        "it-IT": "Bowser Battle 1 (Hurry Up!)",
        "pt-PT": "Bowser Battle 1 (Hurry Up!)",
        "pt-BR": "Bowser Battle 1 (Hurry Up!)",
        "es-ES": "Bowser Battle 1 (Hurry Up!)",
        "es-MX": "Bowser Battle 1 (Hurry Up!)",
        "ru-RU": "Bowser Battle 1 (Hurry Up!)",
        "ko-KR": "Bowser Battle 1 (Hurry Up!)",
        "zh-CN": "Bowser Battle 1 (Hurry Up!)",
        "zh-TW": "Bowser Battle 1 (Hurry Up!)"
      }
    },
    {
      "id": "7c9c4ace-cd67-48a1-ba26-6acaf35d2dde",
      "name": {
        "en-US": "Bowser Battle 2",
        "ja-JP": "クッパ戦 その2",
        "en-GB": "Bowser Battle 2",
        "fr-FR": "Bowser Battle 2",
        "fr-CA": "Bowser Battle 2",
        "de-DE": "Bowser Battle 2",
        "nl-NL": "Bowser Battle 2",
        "it-IT": "Bowser Battle 2",
        "pt-PT": "Bowser Battle 2",
        "pt-BR": "Bowser Battle 2",
        "es-ES": "Bowser Battle 2",
        "es-MX": "Bowser Battle 2",
        "ru-RU": "Bowser Battle 2",
        "ko-KR": "Bowser Battle 2",
        "zh-CN": "Bowser Battle 2",
        "zh-TW": "Bowser Battle 2"
      }
    },
    {
      "id": "6643ffbb-4712-4ab7-a459-9a74f796b833",
      "name": {
        "en-US": "Bowser Battle 2 (Hurry Up!)",
        "ja-JP": "クッパ戦 その2（ハリーアップ）",
        "en-GB": "Bowser Battle 2 (Hurry Up!)",
        "fr-FR": "Bowser Battle 2 (Hurry Up!)",
        "fr-CA": "Bowser Battle 2 (Hurry Up!)",
        "de-DE": "Bowser Battle 2 (Hurry Up!)",
        "nl-NL": "Bowser Battle 2 (Hurry Up!)",
        "it-IT": "Bowser Battle 2 (Hurry Up!)",
        "pt-PT": "Bowser Battle 2 (Hurry Up!)",
        "pt-BR": "Bowser Battle 2 (Hurry Up!)",
        "es-ES": "Bowser Battle 2 (Hurry Up!)",
        "es-MX": "Bowser Battle 2 (Hurry Up!)",
        "ru-RU": "Bowser Battle 2 (Hurry Up!)",
        "ko-KR": "Bowser Battle 2 (Hurry Up!)",
        "zh-CN": "Bowser Battle 2 (Hurry Up!)",
        "zh-TW": "Bowser Battle 2 (Hurry Up!)"
      }
    },
    {
      "id": "dd91987c-1d16-4834-a1d2-2e653b2f3188",
      "name": {
        "en-US": "Bowser Defeated",
        "ja-JP": "クッパ撃破",
        "en-GB": "Bowser Defeated",
        "fr-FR": "Bowser Defeated",
        "fr-CA": "Bowser Defeated",
        "de-DE": "Bowser Defeated",
        "nl-NL": "Bowser Defeated",
        "it-IT": "Bowser Defeated",
        "pt-PT": "Bowser Defeated",
        "pt-BR": "Bowser Defeated",
        "es-ES": "Bowser Defeated",
        "es-MX": "Bowser Defeated",
        "ru-RU": "Bowser Defeated",
        "ko-KR": "Bowser Defeated",
        "zh-CN": "Bowser Defeated",
        "zh-TW": "Bowser Defeated"
      }
    },
    {
      "id": "807148ca-ec05-4123-a7a7-15b227a248ea",
      "name": {
        "en-US": "The Rescue of Princess Peach",
        "ja-JP": "ピーチ姫救出",
        "en-GB": "The Rescue of Princess Peach",
        "fr-FR": "The Rescue of Princess Peach",
        "fr-CA": "The Rescue of Princess Peach",
        "de-DE": "The Rescue of Princess Peach",
        "nl-NL": "The Rescue of Princess Peach",
        "it-IT": "The Rescue of Princess Peach",
        "pt-PT": "The Rescue of Princess Peach",
        "pt-BR": "The Rescue of Princess Peach",
        "es-ES": "The Rescue of Princess Peach",
        "es-MX": "The Rescue of Princess Peach",
        "ru-RU": "The Rescue of Princess Peach",
        "ko-KR": "The Rescue of Princess Peach",
        "zh-CN": "The Rescue of Princess Peach",
        "zh-TW": "The Rescue of Princess Peach"
      }
    },
    {
      "id": "018e53dc-1933-4bd6-8948-7793a97780ed",
      "name": {
        "en-US": "Epilogue",
        "ja-JP": "エピローグ",
        "en-GB": "Epilogue",
        "fr-FR": "Epilogue",
        "fr-CA": "Epilogue",
        "de-DE": "Epilogue",
        "nl-NL": "Epilogue",
        "it-IT": "Epilogue",
        "pt-PT": "Epilogue",
        "pt-BR": "Epilogue",
        "es-ES": "Epilogue",
        "es-MX": "Epilogue",
        "ru-RU": "Epilogue",
        "ko-KR": "Epilogue",
        "zh-CN": "Epilogue",
        "zh-TW": "Epilogue"
      }
    },
    {
      "id": "90b976bf-e31c-4eff-a72e-cd0c89d2f508",
      "name": {
        "en-US": "New Super Mario Bros. U Staff Credits",
        "ja-JP": "New Super Mario Bros. U スタッフクレジット",
        "en-GB": "New Super Mario Bros. U Staff Credits",
        "fr-FR": "New Super Mario Bros. U Staff Credits",
        "fr-CA": "New Super Mario Bros. U Staff Credits",
        "de-DE": "New Super Mario Bros. U Staff Credits",
        "nl-NL": "New Super Mario Bros. U Staff Credits",
        "it-IT": "New Super Mario Bros. U Staff Credits",
        "pt-PT": "New Super Mario Bros. U Staff Credits",
        "pt-BR": "New Super Mario Bros. U Staff Credits",
        "es-ES": "New Super Mario Bros. U Staff Credits",
        "es-MX": "New Super Mario Bros. U Staff Credits",
        "ru-RU": "New Super Mario Bros. U Staff Credits",
        "ko-KR": "New Super Mario Bros. U Staff Credits",
        "zh-CN": "New Super Mario Bros. U Staff Credits",
        "zh-TW": "New Super Mario Bros. U Staff Credits"
      }
    },
    {
      "id": "c0c4a01b-4e8f-4ff7-9d7a-ce83c7af27b5",
      "name": {
        "en-US": "World: Superstar Road",
        "ja-JP": "ワールド：スペシャルスター",
        "en-GB": "World: Superstar Road",
        "fr-FR": "World: Superstar Road",
        "fr-CA": "World: Superstar Road",
        "de-DE": "World: Superstar Road",
        "nl-NL": "World: Superstar Road",
        "it-IT": "World: Superstar Road",
        "pt-PT": "World: Superstar Road",
        "pt-BR": "World: Superstar Road",
        "es-ES": "World: Superstar Road",
        "es-MX": "World: Superstar Road",
        "ru-RU": "World: Superstar Road",
        "ko-KR": "World: Superstar Road",
        "zh-CN": "World: Superstar Road",
        "zh-TW": "World: Superstar Road"
      }
    },
    {
      "id": "9ed913eb-a6c5-4d96-952e-31b3cb4b766c",
      "name": {
        "en-US": "Coin Edit",
        "ja-JP": "コインエディット",
        "en-GB": "Coin Edit",
        "fr-FR": "Coin Edit",
        "fr-CA": "Coin Edit",
        "de-DE": "Coin Edit",
        "nl-NL": "Coin Edit",
        "it-IT": "Coin Edit",
        "pt-PT": "Coin Edit",
        "pt-BR": "Coin Edit",
        "es-ES": "Coin Edit",
        "es-MX": "Coin Edit",
        "ru-RU": "Coin Edit",
        "ko-KR": "Coin Edit",
        "zh-CN": "Coin Edit",
        "zh-TW": "Coin Edit"
      }
    },
    {
      "id": "856ce75f-864f-4071-ada7-4aacfd18412f",
      "name": {
        "en-US": "Results",
        "ja-JP": "リザルト",
        "en-GB": "Results",
        "fr-FR": "Results",
        "fr-CA": "Results",
        "de-DE": "Results",
        "nl-NL": "Results",
        "it-IT": "Results",
        "pt-PT": "Results",
        "pt-BR": "Results",
        "es-ES": "Results",
        "es-MX": "Results",
        "ru-RU": "Results",
        "ko-KR": "Results",
        "zh-CN": "Results",
        "zh-TW": "Results"
      }
    },
    {
      "id": "c0be3faa-dc3a-4ae1-9e86-eeaad3ba93e3",
      "name": {
        "en-US": "Secret Island Record Room",
        "ja-JP": "ひみつのしまのきろく部屋",
        "en-GB": "Secret Island Record Room",
        "fr-FR": "Secret Island Record Room",
        "fr-CA": "Secret Island Record Room",
        "de-DE": "Secret Island Record Room",
        "nl-NL": "Secret Island Record Room",
        "it-IT": "Secret Island Record Room",
        "pt-PT": "Secret Island Record Room",
        "pt-BR": "Secret Island Record Room",
        "es-ES": "Secret Island Record Room",
        "es-MX": "Secret Island Record Room",
        "ru-RU": "Secret Island Record Room",
        "ko-KR": "Secret Island Record Room",
        "zh-CN": "Secret Island Record Room",
        "zh-TW": "Secret Island Record Room"
      }
    },
    {
      "id": "98944b77-5583-4e9a-b3cc-2a8cf6171af2",
      "name": {
        "en-US": "New Super Mario Bros. U Deluxe Staff Credits",
        "ja-JP": "New Super Mario Bros. U Deluxe スタッフクレジット",
        "en-GB": "New Super Mario Bros. U Deluxe Staff Credits",
        "fr-FR": "New Super Mario Bros. U Deluxe Staff Credits",
        "fr-CA": "New Super Mario Bros. U Deluxe Staff Credits",
        "de-DE": "New Super Mario Bros. U Deluxe Staff Credits",
        "nl-NL": "New Super Mario Bros. U Deluxe Staff Credits",
        "it-IT": "New Super Mario Bros. U Deluxe Staff Credits",
        "pt-PT": "New Super Mario Bros. U Deluxe Staff Credits",
        "pt-BR": "New Super Mario Bros. U Deluxe Staff Credits",
        "es-ES": "New Super Mario Bros. U Deluxe Staff Credits",
        "es-MX": "New Super Mario Bros. U Deluxe Staff Credits",
        "ru-RU": "New Super Mario Bros. U Deluxe Staff Credits",
        "ko-KR": "New Super Mario Bros. U Deluxe Staff Credits",
        "zh-CN": "New Super Mario Bros. U Deluxe Staff Credits",
        "zh-TW": "New Super Mario Bros. U Deluxe Staff Credits"
      }
    }
  ],
  "localesWithDistinctTrackNames": [
    "en-US",
    "ja-JP"
  ],
  "localesWithDistinctTrackNamesCount": 2
}